{"filecode":"tsrredw0q5uy","title":"Pemilik Hotel Meniduri Gadis Remaja Di Malam Hari Kamarnya X Hamster","deskripsi":"Nonton Pemilik Hotel Meniduri Gadis Remaja Di Malam Hari Kamarnya X Hamster gratis. Ukuran File: 844.00 MB, Durasi: 14:04. Populer: 7440 tayangan. Diunggah pada 2024-04-05 19:04:27 melalui doodstream. Kata Kunci Terkait: .","tag":null,"protected_embed":"https://dodl.pages.dev/tsrredw0q5uy","protected_dl":"https://myvidplay.com/d/tsrredw0q5uy","single_img":"https://postercdn.net/snaps/yela078d9v3r4y08.jpg","splash_img":"https://postercdn.net/splash/yela078d9v3r4y08.jpg","size":"884998144","length":"844","duration":"PT14M4S","views":"7440","uploaded":"2024-04-05 19:04:27","last_view":"2024-04-05 19:04:27","api_source":"doodstream","kategori":"Video Remaja","page":46,"index":186}