{"filecode":"qsd42gtndtqr","title":"Pakai Seragam Osis Dood Stream Doostream Video Viral Terupdate Doodstream Link Web","deskripsi":"Nonton Pakai Seragam Osis Dood Stream Doostream Video Viral Terupdate Doodstream Link Web gratis. Ukuran File: 676.00 MB, Durasi: 11:16. Populer: 1130 tayangan. Diunggah pada 2023-08-07 22:43:05 melalui doodstream. Kata Kunci Terkait: .","tag":null,"protected_embed":"https://dodl.pages.dev/qsd42gtndtqr","protected_dl":"https://myvidplay.com/d/qsd42gtndtqr","single_img":"https://postercdn.net/snaps/2gzglqrbi7dswcvv.jpg","splash_img":"https://postercdn.net/splash/2gzglqrbi7dswcvv.jpg","size":"708837376","length":"676","duration":"PT11M16S","views":"1130","uploaded":"2023-08-07 22:43:05","last_view":"2023-08-07 22:43:05","api_source":"doodstream","kategori":"Video Viral","page":120,"index":23}