{"filecode":"n3yvrp83ju84","title":"Guru Pns Bokep31 Bokepind Xpanas Tobrut Tiktok","deskripsi":"Nonton Guru Pns Bokep31 Bokepind Xpanas Tobrut Tiktok gratis. Ukuran File: 469.00 MB, Durasi: 07:49. Populer: 23486 tayangan. Diunggah pada 2023-06-14 16:17:29 melalui doodstream. Kata Kunci Terkait: .","tag":null,"protected_embed":"https://dodl.pages.dev/n3yvrp83ju84","protected_dl":"https://myvidplay.com/d/n3yvrp83ju84","single_img":"https://postercdn.net/snaps/sk924kbfiydjrvou.jpg","splash_img":"https://postercdn.net/splash/sk924kbfiydjrvou.jpg","size":"491782144","length":"469","duration":"PT7M49S","views":"23486","uploaded":"2023-06-14 16:17:29","last_view":"2023-06-14 16:17:29","api_source":"doodstream","kategori":"Video Guru","page":135,"index":81}