{"filecode":"xp4vm7051osq","title":"Bokep Indo Tante Mampu Berdenyut Saat Menghisap Lulustream Video Colmek Link Web","deskripsi":"Nonton Bokep Indo Tante Mampu Berdenyut Saat Menghisap Lulustream Video Colmek Link Web gratis. Ukuran File: 120.00 MB, Durasi: 02:00. Populer: 656 tayangan. Diunggah pada 2024-11-22 03:56:59 melalui doodstream. Kata Kunci Terkait: .","tag":null,"protected_embed":"https://dodl.pages.dev/xp4vm7051osq","protected_dl":"https://myvidplay.com/d/xp4vm7051osq","single_img":"https://postercdn.net/snaps/yeejee645z3f03wp.jpg","splash_img":"https://postercdn.net/splash/yeejee645z3f03wp.jpg","size":"125829120","length":"120","duration":"PT2M","views":"656","uploaded":"2024-11-22 03:56:59","last_view":"2024-11-22 03:56:59","api_source":"doodstream","kategori":"Video Indo","page":31,"index":95}