{"filecode":"00to70by8ygg","title":"Acha Viral Di Tiktok Telegram Video Bokep Bochiel Live Memeksiana","deskripsi":"Nonton Acha Viral Di Tiktok Telegram Video Bokep Bochiel Live Memeksiana gratis. Ukuran File: 903.00 MB, Durasi: 15:03. Populer: 65297 tayangan. Diunggah pada 2023-07-07 04:50:44 melalui doodstream. Kata Kunci Terkait: .","tag":null,"protected_embed":"https://dodl.pages.dev/00to70by8ygg","protected_dl":"https://myvidplay.com/d/00to70by8ygg","single_img":"https://postercdn.net/snaps/s2a2efm95f9imjxy.jpg","splash_img":"https://postercdn.net/splash/s2a2efm95f9imjxy.jpg","size":"946864128","length":"903","duration":"PT15M3S","views":"65297","uploaded":"2023-07-07 04:50:44","last_view":"2023-07-07 04:50:44","api_source":"doodstream","kategori":"Video Viral","page":127,"index":34}