{"filecode":"vm22bgu6sjmg","title":"Jilbab Crot Muka Asupan Viral Link Web Lokal Bochiel Video Sma","deskripsi":"Nonton Jilbab Crot Muka Asupan Viral Link Web Lokal Bochiel Video Sma gratis. Ukuran File: 117.00 MB, Durasi: 01:57. Populer: 9420 tayangan. Diunggah pada 2023-12-09 16:49:05 melalui doodstream. Kata Kunci Terkait: .","tag":null,"protected_embed":"https://dodl.pages.dev/vm22bgu6sjmg","protected_dl":"https://myvidplay.com/d/vm22bgu6sjmg","single_img":"https://postercdn.net/snaps/t7ebyldoep4a56st.jpg","splash_img":"https://postercdn.net/splash/t7ebyldoep4a56st.jpg","size":"122683392","length":"117","duration":"PT1M57S","views":"9420","uploaded":"2023-12-09 16:49:05","last_view":"2023-12-09 16:49:05","api_source":"doodstream","kategori":"Video Viral","page":75,"index":99}