{"filecode":"uvx4ffzwslu5","title":"Bokep Indo Onlyfans Susu Gede Pepek Hitam Imsummer Nude Full Video Leak","deskripsi":"Nonton Bokep Indo Onlyfans Susu Gede Pepek Hitam Imsummer Nude Full Video Leak gratis. Ukuran File: 128.00 MB, Durasi: 02:08. Populer: 4658 tayangan. Diunggah pada 2023-08-07 22:11:28 melalui doodstream. Kata Kunci Terkait: .","tag":null,"protected_embed":"https://dodl.pages.dev/uvx4ffzwslu5","protected_dl":"https://myvidplay.com/d/uvx4ffzwslu5","single_img":"https://postercdn.net/snaps/exf788tokybyzdxu.jpg","splash_img":"https://postercdn.net/splash/exf788tokybyzdxu.jpg","size":"134217728","length":"128","duration":"PT2M8S","views":"4658","uploaded":"2023-08-07 22:11:28","last_view":"2023-08-07 22:11:28","api_source":"doodstream","kategori":"Video Indo","page":121,"index":95}