{"filecode":"ic40fk8v8k7i","title":"Bokep Terbaru Tiktokers Ellekampong Ngentot Di Kolam Renang Bokepsin Doods Pro Video","deskripsi":"Nonton Bokep Terbaru Tiktokers Ellekampong Ngentot Di Kolam Renang Bokepsin Doods Pro Video gratis. Ukuran File: 594.00 MB, Durasi: 09:54. Populer: 1989 tayangan. Diunggah pada 2023-12-13 13:29:44 melalui doodstream. Kata Kunci Terkait: .","tag":null,"protected_embed":"https://dodl.pages.dev/ic40fk8v8k7i","protected_dl":"https://myvidplay.com/d/ic40fk8v8k7i","single_img":"https://postercdn.net/snaps/1brx2w7skviif9ql.jpg","splash_img":"https://postercdn.net/splash/1brx2w7skviif9ql.jpg","size":"622854144","length":"594","duration":"PT9M54S","views":"1989","uploaded":"2023-12-13 13:29:44","last_view":"2023-12-13 13:29:44","api_source":"doodstream","kategori":"Video Terbaru","page":71,"index":64}