{"filecode":"m96mkavzozek","title":"Aviva Vids Asupan Viral Doodstreem Cilbo Lulustream Links","deskripsi":"Nonton Aviva Vids Asupan Viral Doodstreem Cilbo Lulustream Links gratis. Ukuran File: 5.00 MB, Durasi: 00:05. Populer: 722 tayangan. Diunggah pada 2025-01-13 05:27:42 melalui doodstream. Kata Kunci Terkait: .","tag":null,"protected_embed":"https://dodl.pages.dev/m96mkavzozek","protected_dl":"https://myvidplay.com/d/m96mkavzozek","single_img":"https://postercdn.net/snaps/6p6b4o8v9o8e3wij.jpg","splash_img":"https://postercdn.net/splash/6p6b4o8v9o8e3wij.jpg","size":"5242880","length":"5","duration":"PT5S","views":"722","uploaded":"2025-01-13 05:27:42","last_view":"2025-01-13 05:27:42","api_source":"doodstream","kategori":"Video Viral","page":22,"index":140}