{"filecode":"2us9z4gyr1nr","title":"Ayu Merlin Telegram Ukhtyohnaughty Poop Hd Doostream Lulustream Dood Tele Pemersatu Update","deskripsi":"Nonton Ayu Merlin Telegram Ukhtyohnaughty Poop Hd Doostream Lulustream Dood Tele Pemersatu Update gratis. Ukuran File: 121.00 MB, Durasi: 02:01. Populer: 3255 tayangan. Diunggah pada 2024-10-20 12:08:21 melalui doodstream. Kata Kunci Terkait: .","tag":null,"protected_embed":"https://dodl.pages.dev/2us9z4gyr1nr","protected_dl":"https://myvidplay.com/d/2us9z4gyr1nr","single_img":"https://postercdn.net/snaps/66ezcwin2dusgxcw.jpg","splash_img":"https://postercdn.net/splash/66ezcwin2dusgxcw.jpg","size":"126877696","length":"121","duration":"PT2M1S","views":"3255","uploaded":"2024-10-20 12:08:21","last_view":"2024-10-20 12:08:21","api_source":"doodstream","kategori":"Video Lulustream","page":33,"index":116}