{"filecode":"jl5e0sdm9tmo","title":"Ajak Pacar Check In Harus Crot Di Luar Doi Takut Hamil Dood","deskripsi":"Nonton Ajak Pacar Check In Harus Crot Di Luar Doi Takut Hamil Dood gratis. Ukuran File: 300.00 MB, Durasi: 05:00. Populer: 2338 tayangan. Diunggah pada 2023-11-25 05:33:38 melalui doodstream. Kata Kunci Terkait: .","tag":null,"protected_embed":"https://dodl.pages.dev/jl5e0sdm9tmo","protected_dl":"https://myvidplay.com/d/jl5e0sdm9tmo","single_img":"https://postercdn.net/snaps/nbwrex2l3gocgg2i.jpg","splash_img":"https://postercdn.net/splash/nbwrex2l3gocgg2i.jpg","size":"314572800","length":"300","duration":"PT5M","views":"2338","uploaded":"2023-11-25 05:33:38","last_view":"2023-11-25 05:33:38","api_source":"doodstream","kategori":"Video Dood","page":81,"index":79}