{"filecode":"0ocmtlcet188","title":"Smp Jilbab Tapi Bohay Telegram Doodstreem Simontok Downloader Folder","deskripsi":"Nonton Smp Jilbab Tapi Bohay Telegram Doodstreem Simontok Downloader Folder gratis. Ukuran File: 265.00 MB, Durasi: 04:25. Populer: 5796 tayangan. Diunggah pada 2023-11-12 20:53:44 melalui doodstream. Kata Kunci Terkait: .","tag":null,"protected_embed":"https://dodl.pages.dev/0ocmtlcet188","protected_dl":"https://myvidplay.com/d/0ocmtlcet188","single_img":"https://postercdn.net/snaps/3mbt5ugbwcj5smjl.jpg","splash_img":"https://postercdn.net/splash/3mbt5ugbwcj5smjl.jpg","size":"277872640","length":"265","duration":"PT4M25S","views":"5796","uploaded":"2023-11-12 20:53:44","last_view":"2023-11-12 20:53:44","api_source":"doodstream","kategori":"Video Telegram","page":84,"index":37}