{"filecode":"pcyu7bd8bb2f","title":"Crot Di Muka Cewek Berhijab Enak Bgt Viral Indo Video Dood Tele","deskripsi":"Nonton Crot Di Muka Cewek Berhijab Enak Bgt Viral Indo Video Dood Tele gratis. Ukuran File: 342.00 MB, Durasi: 05:42. Populer: 400 tayangan. Diunggah pada 2025-01-13 05:20:08 melalui doodstream. Kata Kunci Terkait: .","tag":null,"protected_embed":"https://dodl.pages.dev/pcyu7bd8bb2f","protected_dl":"https://myvidplay.com/d/pcyu7bd8bb2f","single_img":"https://postercdn.net/snaps/ukcru7grbyoxl6fn.jpg","splash_img":"https://postercdn.net/splash/ukcru7grbyoxl6fn.jpg","size":"358612992","length":"342","duration":"PT5M42S","views":"400","uploaded":"2025-01-13 05:20:08","last_view":"2025-01-13 05:20:08","api_source":"doodstream","kategori":"Video Viral","page":27,"index":12}