{"filecode":"av9zl2t03843","title":"Lah Ketagihan Di Twitter Virly Virginia Https T Co Yni X Y","deskripsi":"Nonton Lah Ketagihan Di Twitter Virly Virginia Https T Co Yni X Y gratis. Ukuran File: 99.00 MB, Durasi: 01:39. Populer: 306 tayangan. Diunggah pada 2025-01-13 05:26:23 melalui doodstream. Kata Kunci Terkait: .","tag":null,"protected_embed":"https://dodl.pages.dev/av9zl2t03843","protected_dl":"https://myvidplay.com/d/av9zl2t03843","single_img":"https://postercdn.net/snaps/bypg5qhi4tbl2oqf.jpg","splash_img":"https://postercdn.net/splash/bypg5qhi4tbl2oqf.jpg","size":"103809024","length":"99","duration":"PT1M39S","views":"306","uploaded":"2025-01-13 05:26:23","last_view":"2025-01-13 05:26:23","api_source":"doodstream","kategori":"Video Twitter","page":23,"index":155}