{"filecode":"y1sw2hxt9dgm","title":"Toketnya Gede Banget Mulus Lagi Sotwe Doods Pro Jilbab Tele Bokep","deskripsi":"Nonton Toketnya Gede Banget Mulus Lagi Sotwe Doods Pro Jilbab Tele Bokep gratis. Ukuran File: 97.00 MB, Durasi: 01:37. Populer: 84 tayangan. Diunggah pada 2025-01-13 05:24:39 melalui doodstream. Kata Kunci Terkait: .","tag":null,"protected_embed":"https://dodl.pages.dev/y1sw2hxt9dgm","protected_dl":"https://myvidplay.com/d/y1sw2hxt9dgm","single_img":"https://postercdn.net/snaps/onjuglp5pxwxrsph.jpg","splash_img":"https://postercdn.net/splash/onjuglp5pxwxrsph.jpg","size":"101711872","length":"97","duration":"PT1M37S","views":"84","uploaded":"2025-01-13 05:24:39","last_view":"2025-01-13 05:24:39","api_source":"doodstream","kategori":"Video Bokep","page":24,"index":48}