{"filecode":"4cclyr8szja7","title":"Pijat Plus Nikmat Kocokin Kontol Gede Bokep Indo Viral Twitter Asupan Doods","deskripsi":"Nonton Pijat Plus Nikmat Kocokin Kontol Gede Bokep Indo Viral Twitter Asupan Doods gratis. Ukuran File: 369.00 MB, Durasi: 06:09. Populer: 2555 tayangan. Diunggah pada 2023-11-12 20:57:37 melalui doodstream. Kata Kunci Terkait: .","tag":null,"protected_embed":"https://dodl.pages.dev/4cclyr8szja7","protected_dl":"https://myvidplay.com/d/4cclyr8szja7","single_img":"https://postercdn.net/snaps/qayi63hdvwr6r6ys.jpg","splash_img":"https://postercdn.net/splash/qayi63hdvwr6r6ys.jpg","size":"386924544","length":"369","duration":"PT6M9S","views":"2555","uploaded":"2023-11-12 20:57:37","last_view":"2023-11-12 20:57:37","api_source":"doodstream","kategori":"Video Viral","page":83,"index":196}