{"filecode":"xooon7jmoyi3","title":"Janda Hijab Tubuhnya Rela Dipakai Dood Stream Asupan Viral Xpanas Bokepsatset Website","deskripsi":"Nonton Janda Hijab Tubuhnya Rela Dipakai Dood Stream Asupan Viral Xpanas Bokepsatset Website gratis. Ukuran File: 513.00 MB, Durasi: 08:33. Populer: 1264 tayangan. Diunggah pada 2023-10-22 16:52:03 melalui doodstream. Kata Kunci Terkait: .","tag":null,"protected_embed":"https://dodl.pages.dev/xooon7jmoyi3","protected_dl":"https://myvidplay.com/d/xooon7jmoyi3","single_img":"https://postercdn.net/snaps/3hn74hreaezzag55.jpg","splash_img":"https://postercdn.net/splash/3hn74hreaezzag55.jpg","size":"537919488","length":"513","duration":"PT8M33S","views":"1264","uploaded":"2023-10-22 16:52:03","last_view":"2023-10-22 16:52:03","api_source":"doodstream","kategori":"Video Hijab","page":91,"index":149}