{"filecode":"bxipzyhl3gfy","title":"Bokep Barat Ayah Dan Anak Kelly Divine Video Terbaru Jilbab Indo Simontok","deskripsi":"Nonton Bokep Barat Ayah Dan Anak Kelly Divine Video Terbaru Jilbab Indo Simontok gratis. Ukuran File: 720.00 MB, Durasi: 12:00. Populer: 1945 tayangan. Diunggah pada 2023-12-11 12:53:40 melalui doodstream. Kata Kunci Terkait: .","tag":null,"protected_embed":"https://dodl.pages.dev/bxipzyhl3gfy","protected_dl":"https://myvidplay.com/d/bxipzyhl3gfy","single_img":"https://postercdn.net/snaps/2cnjopy35vqrxt5c.jpg","splash_img":"https://postercdn.net/splash/2cnjopy35vqrxt5c.jpg","size":"754974720","length":"720","duration":"PT12M","views":"1945","uploaded":"2023-12-11 12:53:40","last_view":"2023-12-11 12:53:40","api_source":"doodstream","kategori":"Video Terbaru","page":73,"index":6}