{"page":37,"per_page":200,"total":27309,"total_pages":137,"data":[{"download_url":"https://myvidplay.com/d/5gsvq6yeigdd","single_img":"https://postercdn.net/snaps/v77t2jwp53dnuzi2.jpg","file_code":"5gsvq6yeigdd","length":"599","views":"457","uploaded":"2024-08-31 14:43:32","title":"Bokep Indo Abg Masih Bocil Udah Belajar Colmek Doodstreem Simintok Xpanas Doodstream"},{"download_url":"https://myvidplay.com/d/lgn9io6rf9tc","single_img":"https://postercdn.net/snaps/gb3566zmlpia3jo2.jpg","file_code":"lgn9io6rf9tc","length":"98","views":"347","uploaded":"2024-08-31 14:43:32","title":"Bokep Indo Bocil Cantik Turun Naik Botol Rexona Ngentot Pekoblive Downloader Video"},{"download_url":"https://myvidplay.com/d/r22alc9ywdsf","single_img":"https://postercdn.net/snaps/caij8k6bp0332xqj.jpg","file_code":"r22alc9ywdsf","length":"63","views":"131","uploaded":"2024-08-31 14:43:32","title":"Bokep Indo Bocil Colok Memek Pake Sikat Gigi Viral Cantik Tobrut Full"},{"download_url":"https://myvidplay.com/d/sixrl14moizc","single_img":"https://postercdn.net/snaps/akl10meoqdogo5tu.jpg","file_code":"sixrl14moizc","length":"313","views":"488","uploaded":"2024-08-31 14:43:32","title":"Bokep Indo Ngentot Sama Ayang Bocil Di Kamar Video Viral Xpanas Doodsflix"},{"download_url":"https://myvidplay.com/d/5cc6s04ilti0","single_img":"https://postercdn.net/snaps/2hx5tp9rb3u5gweh.jpg","file_code":"5cc6s04ilti0","length":"207","views":"143","uploaded":"2024-08-31 14:43:32","title":"Bokep Indo Zua Bocil Lepas Hijab Colmek Simintok Simontok Website Video"},{"download_url":"https://myvidplay.com/d/iyiolxl9rtvo","single_img":"https://postercdn.net/snaps/yaqc1wq2kusqophi.jpg","file_code":"iyiolxl9rtvo","length":"167","views":"277","uploaded":"2024-08-31 14:43:32","title":"Bokep Indo Bocil Cindo Cantik Sange Colok Memek Dood Xpanas Simintok Streaming"},{"download_url":"https://myvidplay.com/d/gmd21r0fg85b","single_img":"https://postercdn.net/snaps/foihbjvs9p9y68zt.jpg","file_code":"gmd21r0fg85b","length":"63","views":"607","uploaded":"2024-08-31 14:43:32","title":"Bokep Indo Kiyya Bocil Wot Bantal Guling Twitter Yakwad Ngentot Memeksiana Folder"},{"download_url":"https://myvidplay.com/d/79b9bdoq94ax","single_img":"https://postercdn.net/snaps/yph7tdrfbflv53lv.jpg","file_code":"79b9bdoq94ax","length":"63","views":"1138","uploaded":"2024-08-31 14:43:32","title":"Bokep Indo Bocil Rambut Pendek Belajar Wot Guling Xpanas Doodsflix Tele Pejuang"},{"download_url":"https://myvidplay.com/d/ymzc6miinep9","single_img":"https://postercdn.net/snaps/nq9at9mhj0t3rd7j.jpg","file_code":"ymzc6miinep9","length":"480","views":"571","uploaded":"2024-08-31 14:43:32","title":"Bokep Kakak Adek Live Lesbi Demi Saweran Pemersatu Jilbab Bokepin Folder"},{"download_url":"https://myvidplay.com/d/76waju4xfn8l","single_img":"https://postercdn.net/snaps/gwgwjaw96o1h0i6u.jpg","file_code":"76waju4xfn8l","length":"162","views":"493","uploaded":"2024-08-31 14:43:25","title":"Bokep Ngewe Gayatrie Adek Sepupu Di Bandung Links Viral Lokal Pemersatu Full"},{"download_url":"https://myvidplay.com/d/pl7jyv5dib55","single_img":"https://postercdn.net/snaps/dz9qtg5t8cri9bzp.jpg","file_code":"pl7jyv5dib55","length":"1141","views":"3653","uploaded":"2024-08-31 14:43:25","title":"Bokep Cewek Teman Digilir Saat Mabok Sotwe Video Bokepin Lulustream Asupan Viral"},{"download_url":"https://myvidplay.com/d/mk68cf33uxsy","single_img":"https://postercdn.net/snaps/6gmh46s26jku07y8.jpg","file_code":"mk68cf33uxsy","length":"78","views":"499","uploaded":"2024-08-31 14:43:25","title":"Bokep Di Perkosa Temen Cowo Tele Dodstream Video Streaming Website"},{"download_url":"https://myvidplay.com/d/qq7nsrft3fgq","single_img":"https://postercdn.net/snaps/g78l9b44l2f1p70k.jpg","file_code":"qq7nsrft3fgq","length":"165","views":"1198","uploaded":"2024-08-31 14:43:25","title":"Bokep Indo Perkosa Chindo Jerit Mendesah Kesakitan Update Ngentot Toketbagus Dood Tele"},{"download_url":"https://myvidplay.com/d/pdkbzl81cjj7","single_img":"https://postercdn.net/snaps/v7axxjfkh5im4r4a.jpg","file_code":"pdkbzl81cjj7","length":"93","views":"248","uploaded":"2024-08-31 14:43:25","title":"Bokep Gangbang Adik Rame Cewe Cantik Abg Doods Pro Memeksiana Tobrut Telegram"},{"download_url":"https://myvidplay.com/d/zjqhzftegc7i","single_img":"https://postercdn.net/snaps/55wdv8uw5ktvkfkh.jpg","file_code":"zjqhzftegc7i","length":"457","views":"1043","uploaded":"2024-08-31 14:43:25","title":"Bokep Hijab Tobrut Ngentot Lesbian Viral Simintok Downloader Lulustream Toketbagus Doodflix"},{"download_url":"https://myvidplay.com/d/x7aoccctra7d","single_img":"https://postercdn.net/snaps/4siratxdyhtj9b8c.jpg","file_code":"x7aoccctra7d","length":"161","views":"1958","uploaded":"2024-08-31 14:43:25","title":"Bokep Perkosa Teman Cantik Lagi Mabok Bokepind Video Dodstream Telegram Doods Pro"},{"download_url":"https://myvidplay.com/d/oizchkf62j7c","single_img":"https://postercdn.net/snaps/cty1z7fx67808dqz.jpg","file_code":"oizchkf62j7c","length":"1861","views":"383","uploaded":"2024-08-31 14:43:25","title":"Bokep Jamilah Tobrut Ngewe Layani Orang Tele Telegram Bokepsatset Doostream Video"},{"download_url":"https://myvidplay.com/d/1gzervafxxc3","single_img":"https://postercdn.net/snaps/8wymqxjelo4qotdh.jpg","file_code":"1gzervafxxc3","length":"106","views":"2452","uploaded":"2024-08-31 14:43:25","title":"Bokep Grepe Rame Pas Karaoke Folder Indonesia Full Album Links Viral"},{"download_url":"https://myvidplay.com/d/lspvud3jfpga","single_img":"https://postercdn.net/snaps/rbn6xnhxycuubcfm.jpg","file_code":"lspvud3jfpga","length":"524","views":"1236","uploaded":"2024-08-31 14:43:25","title":"Bokep Cantik Live Lesbian Teman Full Album Indonesia Bokepsatset Terupdate Video Indo"},{"download_url":"https://myvidplay.com/d/ne8rwieirfnr","single_img":"https://postercdn.net/snaps/j25v86s7zggsupiq.jpg","file_code":"ne8rwieirfnr","length":"68","views":"693","uploaded":"2024-08-31 14:43:25","title":"Bokep Paksa Bugil Teman Rame Pejuang Lendir Ngentot Dood Bokepsin Link Web"},{"download_url":"https://myvidplay.com/d/gi9kd5t9uw4y","single_img":"https://postercdn.net/snaps/9t9sp39ts785ifoz.jpg","file_code":"gi9kd5t9uw4y","length":"34","views":"214","uploaded":"2024-08-31 14:43:25","title":"Bokep Pacar Temen Dipakek Rame Telegram Popstream Jilbab Cantik Tobrut Memeksiana"},{"download_url":"https://myvidplay.com/d/7fmfj3zgks02","single_img":"https://postercdn.net/snaps/223ybyrqn91om6ri.jpg","file_code":"7fmfj3zgks02","length":"3010","views":"709","uploaded":"2024-08-31 14:43:25","title":"Bokep Pesta Sex Ngentotin Cewek Rame Sotwe Video Indo Doods Pro Bokepind"},{"download_url":"https://myvidplay.com/d/18o7gvge83e6","single_img":"https://postercdn.net/snaps/o1ks5ytkcqltuhbd.jpg","file_code":"18o7gvge83e6","length":"95","views":"829","uploaded":"2024-08-31 14:43:25","title":"Bokep Temen Bocil Ngewe Di Gubuk Rame Doostream Dood Tele Simontok Indonesia"},{"download_url":"https://myvidplay.com/d/j6rhol51by9u","single_img":"https://postercdn.net/snaps/0umed05t0c8ni9ol.jpg","file_code":"j6rhol51by9u","length":"142","views":"526","uploaded":"2024-08-31 14:43:25","title":"Bokep Abg Bocil Dientod Rame Video Colmek Bokepsin Asupan Dood Lulustream"},{"download_url":"https://myvidplay.com/d/ten3n1z4fb07","single_img":"https://postercdn.net/snaps/94d95475evhkyl9o.jpg","file_code":"ten3n1z4fb07","length":"2165","views":"605","uploaded":"2024-08-31 14:43:25","title":"Bokep Gangbang Cewe Abg Cantik Dood Tele Bokepsin Bokep31 Video"},{"download_url":"https://myvidplay.com/d/gzsa6qhf5mgu","single_img":"https://postercdn.net/snaps/o7xt0l3v2e35yov4.jpg","file_code":"gzsa6qhf5mgu","length":"122","views":"1304","uploaded":"2024-08-31 14:43:25","title":"Bokep Indo Cewek Gemuk Digilir Rame Tobrut Dood Twitter Dodstream Doods Pro"},{"download_url":"https://myvidplay.com/d/2x3vr1zphpz8","single_img":"https://postercdn.net/snaps/dfksf36kga9woi3v.jpg","file_code":"2x3vr1zphpz8","length":"131","views":"1856","uploaded":"2024-08-31 14:43:25","title":"Bokep Chindo Abg Dipaksa Cowonya Rame Bokepsin Pemersatu Doodflix Dood Cantik Tobrut"},{"download_url":"https://myvidplay.com/d/r2icfhvjzuw4","single_img":"https://postercdn.net/snaps/o9oszo1htvgzl88q.jpg","file_code":"r2icfhvjzuw4","length":"28","views":"374","uploaded":"2024-08-31 14:43:25","title":"Bokep Gangbang Abg Fatin Liyana Mangap Keenakan Telegram Bokepsin Tobrut Link Web"},{"download_url":"https://myvidplay.com/d/jnohuakdxu72","single_img":"https://postercdn.net/snaps/8uq0ddvys9xdrwpm.jpg","file_code":"jnohuakdxu72","length":"1493","views":"1651","uploaded":"2024-08-31 14:43:25","title":"Bokep Gangbang Tante Toge Montok Viral Staklam Bokepsin Bochiel Terabox"},{"download_url":"https://myvidplay.com/d/3o52kcqmsl8k","single_img":"https://postercdn.net/snaps/xc8yaq8gsoereml7.jpg","file_code":"3o52kcqmsl8k","length":"480","views":"258","uploaded":"2024-08-31 14:43:25","title":"Bokep Pesta Ngewe Teman Sendiri Lokal Tele Asupan Viral Bebasindo Bochiel"},{"download_url":"https://myvidplay.com/d/ay8b5uyr4jtg","single_img":"https://postercdn.net/snaps/98xrbzlywkoy41uo.jpg","file_code":"ay8b5uyr4jtg","length":"1709","views":"427","uploaded":"2024-08-31 14:43:25","title":"Bokep Live Ngentot Anal Memek Rame Video Viral Dood Twitter Folder"},{"download_url":"https://myvidplay.com/d/lvnvm6jqar6d","single_img":"https://postercdn.net/snaps/v1etqnqwaqplj9rh.jpg","file_code":"lvnvm6jqar6d","length":"1647","views":"427","uploaded":"2024-08-31 14:43:25","title":"Bokep Ngentot Rame Foursome Lebih Nikmat Telegram Bokepsin Dood Dodstream Cilbo"},{"download_url":"https://myvidplay.com/d/rrxn1b1grs7c","single_img":"https://postercdn.net/snaps/mqcaxjn3w9p7b4dx.jpg","file_code":"rrxn1b1grs7c","length":"148","views":"951","uploaded":"2024-08-31 14:43:25","title":"Bokep Di Sikat Temen Hutan Rame Simontok Twitter Bokepsatset Simintok Asupan Viral"},{"download_url":"https://myvidplay.com/d/2i39ipse9b0f","single_img":"https://postercdn.net/snaps/hnnpszh6gr1ygp6o.jpg","file_code":"2i39ipse9b0f","length":"1980","views":"425","uploaded":"2024-08-31 14:43:25","title":"Bokep Live Rame Temen Ngentot Diketawain Bigo Link Web Bochiel Pemersatu Lagi"},{"download_url":"https://myvidplay.com/d/k6qk7ik1ey67","single_img":"https://postercdn.net/snaps/colp445x8g16s47m.jpg","file_code":"k6qk7ik1ey67","length":"2125","views":"332","uploaded":"2024-08-31 14:43:25","title":"Bokep Di Entot Rame Sampe Lemes Live Simontok Ngentot Telegram Streaming"},{"download_url":"https://myvidplay.com/d/gzplwv5d8kra","single_img":"https://postercdn.net/snaps/mni0x1yov85t32ez.jpg","file_code":"gzplwv5d8kra","length":"96","views":"226","uploaded":"2024-08-31 14:43:25","title":"Bokep Smk Ngentot Rame Di Hutan Cilbo Asupan Viral Video Colmek Dood"},{"download_url":"https://myvidplay.com/d/alx5hl4sakb8","single_img":"https://postercdn.net/snaps/jh9itca19lve53pp.jpg","file_code":"alx5hl4sakb8","length":"180","views":"356","uploaded":"2024-08-31 14:43:25","title":"Bokep Abg Lesbi Rame Pekoblive Dood Memeksiana Lokal"},{"download_url":"https://myvidplay.com/d/khqqwt4viyew","single_img":"https://postercdn.net/snaps/3esla7c3apruwn3n.jpg","file_code":"khqqwt4viyew","length":"4323","views":"620","uploaded":"2024-08-31 14:43:25","title":"Bokep Ngewe Cewek Cantik Rame Xpanas Folder Memeksiana Bokepsatset Update"},{"download_url":"https://myvidplay.com/d/hagr95b0bipw","single_img":"https://postercdn.net/snaps/wuxfvfzbbog5yt1w.jpg","file_code":"hagr95b0bipw","length":"858","views":"414","uploaded":"2024-08-31 14:43:25","title":"Bokep Cewek Ngewe Rame Live Downloader Video Viral Indo Doods Pro Staklam"},{"download_url":"https://myvidplay.com/d/mwt3k8vft4sr","single_img":"https://postercdn.net/snaps/meghrn0myx91ps0f.jpg","file_code":"mwt3k8vft4sr","length":"49","views":"606","uploaded":"2024-08-31 14:43:25","title":"Bokep Binor Hijab Dipake Rame Ngentot Asupan Viral Doodstreem Doostream Dood"},{"download_url":"https://myvidplay.com/d/hal01cs7b1se","single_img":"https://postercdn.net/snaps/pa964r0e8rc3so6c.jpg","file_code":"hal01cs7b1se","length":"165","views":"527","uploaded":"2024-08-31 14:43:25","title":"Bokep Viral Bule Dibali Gangbang Rame Terabox Video Cantik Tobrut Terupdate Pekoblive"},{"download_url":"https://myvidplay.com/d/ev911v5f7g8b","single_img":"https://postercdn.net/snaps/lxw1rcad18hx4pky.jpg","file_code":"ev911v5f7g8b","length":"526","views":"311","uploaded":"2024-08-31 14:43:25","title":"Bokep Ayu Ngentot Kawan Live Rame Poophd Doodstreem Bokepind Update Terabox"},{"download_url":"https://myvidplay.com/d/yfl3y4k40vc7","single_img":"https://postercdn.net/snaps/hwfvkscft9ulxz89.jpg","file_code":"yfl3y4k40vc7","length":"3600","views":"853","uploaded":"2024-08-31 14:43:25","title":"Bokep Abg Live Lesbi Rame Doods Pro Bokepsatset Yakwad Video Viral Asupan"},{"download_url":"https://myvidplay.com/d/zgez257um5vu","single_img":"https://postercdn.net/snaps/1ptc4wrmiohpcylm.jpg","file_code":"zgez257um5vu","length":"97","views":"631","uploaded":"2024-08-31 14:43:25","title":"Bokep Smp Ngentot Temen Jilbab Rame Pejuang Lendir Pekoblive Bokep31 Downloader Simintok"},{"download_url":"https://myvidplay.com/d/7tlv171vbj00","single_img":"https://postercdn.net/snaps/uu8oa4ppl9o6f85v.jpg","file_code":"7tlv171vbj00","length":"127","views":"3096","uploaded":"2024-08-31 14:43:25","title":"Bokep Indo Ngentot Bunda Denna Rame Pemuda Kos Lokal Bochiel Website Tobrut"},{"download_url":"https://myvidplay.com/d/f66eiyahh2qy","single_img":"https://postercdn.net/snaps/rooteu7gj3ggjza9.jpg","file_code":"f66eiyahh2qy","length":"276","views":"2908","uploaded":"2024-08-31 14:43:25","title":"Bokep Abg Memek Mulus Di Gangbang Doods Pro Terupdate Cantik Tobrut Simontok"},{"download_url":"https://myvidplay.com/d/abgmzz09ckkm","single_img":"https://postercdn.net/snaps/v6aj7qd844lkgxgc.jpg","file_code":"abgmzz09ckkm","length":"1996","views":"729","uploaded":"2024-08-31 14:43:25","title":"Bokep Papaya Live Show Rame Dgn Temen Kos Jilbab Telegram Streaming Bokepsin"},{"download_url":"https://myvidplay.com/d/1rsydejqr2qa","single_img":"https://postercdn.net/snaps/mqtaasqgjxejvdbb.jpg","file_code":"1rsydejqr2qa","length":"637","views":"4008","uploaded":"2024-08-31 14:43:25","title":"Bokep Mabuk Abg Tak Sadar Gangbang Rame Dood Tele Lagi Viral Bokepin"},{"download_url":"https://myvidplay.com/d/fvmwmehfoe4d","single_img":"https://postercdn.net/snaps/sekr2bvo8rk0d62b.jpg","file_code":"fvmwmehfoe4d","length":"2075","views":"914","uploaded":"2024-08-31 14:43:25","title":"Bokep Indo Abg Pesta Seks Ml Rame Simontok Live Twitter Xpanas Video"},{"download_url":"https://myvidplay.com/d/rv17sjbu9zas","single_img":"https://postercdn.net/snaps/lfcer0w5b9aqlw13.jpg","file_code":"rv17sjbu9zas","length":"378","views":"1520","uploaded":"2024-08-31 14:43:25","title":"Bokep Abg Gangbang Rame Bokepsatset Cilbo Indo Video"},{"download_url":"https://myvidplay.com/d/p393ztqy7p8e","single_img":"https://postercdn.net/snaps/57ulzkuys9k51ttz.jpg","file_code":"p393ztqy7p8e","length":"145","views":"321","uploaded":"2024-08-31 14:43:25","title":"Bokep Indo Ngentot Jilbab Masker Di Hotel Bokepsin Com Website Pemersatu Full"},{"download_url":"https://myvidplay.com/d/isetlyupfedk","single_img":"https://postercdn.net/snaps/e7fv3uvg5s1974st.jpg","file_code":"isetlyupfedk","length":"61","views":"408","uploaded":"2024-08-31 14:43:25","title":"Bokep Indo Rara Nadifa Gadis Abg Viral Bokepsin Dood Stream Doodsflix Video"},{"download_url":"https://myvidplay.com/d/c85fvlx7wy9n","single_img":"https://postercdn.net/snaps/upjpdqv3r6xj2pff.jpg","file_code":"c85fvlx7wy9n","length":"172","views":"2346","uploaded":"2024-08-31 14:43:17","title":"Bokep Arachuu Viral Pramuka Telegram Bokepsin Doodstreem Poophd Doostream Indonesia Doodflix"},{"download_url":"https://myvidplay.com/d/k5aogvxfwpgi","single_img":"https://postercdn.net/snaps/a0gto8vtf9suv9d6.jpg","file_code":"k5aogvxfwpgi","length":"5013","views":"949","uploaded":"2024-08-31 14:43:17","title":"Bokep Kenyot Tetek Miss Octa Lanjut Ml Live Bokepsin Com Indonesia Staklam"},{"download_url":"https://myvidplay.com/d/98murt0qu9a1","single_img":"https://postercdn.net/snaps/jci1j0txp3hwp9u1.jpg","file_code":"98murt0qu9a1","length":"1542","views":"210","uploaded":"2024-08-31 14:43:17","title":"Bokep Citra Hijab Mode Ukhty Live Show Bokepsin Com Tobrut Lagi Viral"},{"download_url":"https://myvidplay.com/d/gl0etsgw5o2r","single_img":"https://postercdn.net/snaps/dchgm8ss3fa9kdhv.jpg","file_code":"gl0etsgw5o2r","length":"149","views":"1145","uploaded":"2024-08-31 14:43:17","title":"Bokep Terbaru Baru Kenalan Udah Diajak Ngentot Bokepsin Com Lokal Doodflix Bokep31"},{"download_url":"https://myvidplay.com/d/89t2sn6f23f8","single_img":"https://postercdn.net/snaps/2rg86wazsv8qrka9.jpg","file_code":"89t2sn6f23f8","length":"145","views":"1351","uploaded":"2024-08-31 14:43:17","title":"Bokep Indo Lisa Chan Hana Tiktok Viral Bokepsin Lulustream Video Sma Doodflix"},{"download_url":"https://myvidplay.com/d/2j0b0siybewg","single_img":"https://postercdn.net/snaps/3j77fpydz70fc3k0.jpg","file_code":"2j0b0siybewg","length":"134","views":"401","uploaded":"2024-08-31 14:43:17","title":"Bokep Ngentot Abg Bertubuh Mungil Idaman Phea Thaiii Bokepsin Telegram Twitter Video"},{"download_url":"https://myvidplay.com/d/12zk3u4493pe","single_img":"https://postercdn.net/snaps/vy6mxl0odvqklmp6.jpg","file_code":"12zk3u4493pe","length":"69","views":"377","uploaded":"2024-08-31 14:43:17","title":"Bokep Queen Hijab Toge Colmek Masih Smp Bokepsin Folder Xpanas Simontok Asupan"},{"download_url":"https://myvidplay.com/d/sv38d8vv607u","single_img":"https://postercdn.net/snaps/5hr0fmt8mxngfawe.jpg","file_code":"sv38d8vv607u","length":"66","views":"3476","uploaded":"2024-08-31 14:43:17","title":"Bokep Syakirah Di Mobil Bokepsin Video Indonesia Doodstream Doods Pro Bokepind"},{"download_url":"https://myvidplay.com/d/g9h3yaw936xo","single_img":"https://postercdn.net/snaps/a58hi5qgvt4l5ryv.jpg","file_code":"g9h3yaw936xo","length":"199","views":"2451","uploaded":"2024-08-31 14:43:17","title":"Smp Ngentod Di Pondok Crot Didalam Dood Stream Downloader Viral Xpanas Tele"},{"download_url":"https://myvidplay.com/d/utj3mo0n3kl3","single_img":"https://postercdn.net/snaps/fkjrq5sfar6md1sh.jpg","file_code":"utj3mo0n3kl3","length":"122","views":"1923","uploaded":"2024-08-31 14:43:17","title":"Bokep Indo Abg Smp Tobrut Baju Putih Bokepsin Cantik Simintok Update Poophd"},{"download_url":"https://myvidplay.com/d/eix2ey74j1iu","single_img":"https://postercdn.net/snaps/ntqi7zfdk6h7r0tz.jpg","file_code":"eix2ey74j1iu","length":"140","views":"332","uploaded":"2024-08-31 14:43:17","title":"Bokep Indo Entot Memek Rapet Abg Smp Pov Bokepsin Toketbagus Twitter Indonesia"},{"download_url":"https://myvidplay.com/d/kn0ozkhihg7s","single_img":"https://postercdn.net/snaps/t1udsz4fpcppqmul.jpg","file_code":"kn0ozkhihg7s","length":"1326","views":"485","uploaded":"2024-08-31 14:43:17","title":"Bokep Indo Gadis Smp Masih Perawan Disewa Om Bokepsin Staklam Lulustream Dood"},{"download_url":"https://myvidplay.com/d/pme65h3vuevd","single_img":"https://postercdn.net/snaps/2rwmndi0m8ct00h7.jpg","file_code":"pme65h3vuevd","length":"1776","views":"2756","uploaded":"2024-08-31 14:43:17","title":"Bokep Indo Murid Smp Guru Olahraga Bokepsin Video Colmek Terabox Doodstreem Dood"},{"download_url":"https://myvidplay.com/d/omp2rpklv438","single_img":"https://postercdn.net/snaps/p8541e8btmy88vlu.jpg","file_code":"omp2rpklv438","length":"125","views":"1306","uploaded":"2024-08-31 14:43:17","title":"Bokep Smp Toge Sama Om Crot Didalam Bokepsin Lulustream Doodstreem Telegram Video"},{"download_url":"https://myvidplay.com/d/mvgxmwtm3eg0","single_img":"https://postercdn.net/snaps/0hxhfcjo162uyz6q.jpg","file_code":"mvgxmwtm3eg0","length":"3177","views":"1934","uploaded":"2024-08-31 14:43:17","title":"Amel Clumsy Prank Tukang Pijat Di Sepongin Bokepsin Dood Stream Toketbagus Live"},{"download_url":"https://myvidplay.com/d/hsqp28oc5jei","single_img":"https://postercdn.net/snaps/zupsbjz5szpynfuu.jpg","file_code":"hsqp28oc5jei","length":"1376","views":"218","uploaded":"2024-08-31 14:43:17","title":"Bokep Indo Abg Service Dari Kakak Istimewa Jago Wot Video Doodstream Folder"},{"download_url":"https://myvidplay.com/d/f6jnvlmxo8xv","single_img":"https://postercdn.net/snaps/n05o4fg1azqe84dd.jpg","file_code":"f6jnvlmxo8xv","length":"810","views":"218","uploaded":"2024-08-31 14:43:17","title":"Nabil Toket Gede Bulat Kenceng Bokepsin Com Doodstream Video Indo Simintok Pekoblive"},{"download_url":"https://myvidplay.com/d/jio1vuslacao","single_img":"https://postercdn.net/snaps/uygk9wbdvjalqb3o.jpg","file_code":"jio1vuslacao","length":"1486","views":"280","uploaded":"2024-08-31 14:43:17","title":"Remaja Putri Cantik Ngocok Memek Becek Bokepsin Com Memeksiana Poophd Doostream Pejuang"},{"download_url":"https://myvidplay.com/d/kdgqq9g5uwte","single_img":"https://postercdn.net/snaps/ltxe8bf27aq3g8ef.jpg","file_code":"kdgqq9g5uwte","length":"210","views":"177","uploaded":"2024-08-31 14:43:17","title":"Model Bugil Viral Paling Banyak Dicari Bokepsin Com Doods Pro Tiktok Videos"},{"download_url":"https://myvidplay.com/d/ork4ar48nsom","single_img":"https://postercdn.net/snaps/191nsvif14brav9p.jpg","file_code":"ork4ar48nsom","length":"472","views":"69","uploaded":"2024-08-31 14:43:17","title":"Sugarbaby Toge Colmek Live Bokepsin Com Memeksiana Lokal Bebasindo Folder Pekoblive"},{"download_url":"https://myvidplay.com/d/6e4c6o8kx2dl","single_img":"https://postercdn.net/snaps/aebmpebgd74zndwi.jpg","file_code":"6e4c6o8kx2dl","length":"900","views":"382","uploaded":"2024-08-31 14:43:17","title":"Cosplay Pramugari Ngentot Tentara Bokepsin Asupan Dood Jilbab Ful Album Doodsflix"},{"download_url":"https://myvidplay.com/d/en40vdkq1yna","single_img":"https://postercdn.net/snaps/f2z77k2n7heoi587.jpg","file_code":"en40vdkq1yna","length":"642","views":"4581","uploaded":"2024-08-31 14:43:17","title":"Bokep Cewek Colmek Dildo Onlyfans Praewasian Video Viral Links Jilbab Sotwe Pejuang"},{"download_url":"https://myvidplay.com/d/v7hmn2k9c2lg","single_img":"https://postercdn.net/snaps/dst3caprgnzezdv2.jpg","file_code":"v7hmn2k9c2lg","length":"773","views":"216","uploaded":"2024-08-31 14:43:17","title":"Bokep Indo Staycation Di Hotel Desa Bambu Bokepsin Com Simintok Video Colmek"},{"download_url":"https://myvidplay.com/d/2qg3qzlhtm51","single_img":"https://postercdn.net/snaps/gb5r3ls6kbgty8ka.jpg","file_code":"2qg3qzlhtm51","length":"281","views":"760","uploaded":"2024-08-31 14:43:17","title":"Bokep Indo Zizi Cantik Toge Colmek Bikin Sange Bokepsin Com Pemersatu Bokepin"},{"download_url":"https://myvidplay.com/d/yibeqn3l2xkm","single_img":"https://postercdn.net/snaps/dy9u0c4hoaagfcia.jpg","file_code":"yibeqn3l2xkm","length":"648","views":"181","uploaded":"2024-08-31 14:43:17","title":"Cewek Jilbab Minta Ngewe Anal Sampai Prot Bokepsin Com Streaming Website Lokal"},{"download_url":"https://myvidplay.com/d/6tysuegnm4u4","single_img":"https://postercdn.net/snaps/n8lphdcvhvo4tica.jpg","file_code":"6tysuegnm4u4","length":"520","views":"3213","uploaded":"2024-08-31 14:43:17","title":"Bokep Indo Remaja Smp Diperkosa Maling Bokepsin Com Telegram Asupan Viral Yakwad"},{"download_url":"https://myvidplay.com/d/3xif1ci7qvjg","single_img":"https://postercdn.net/snaps/hrrpuycawsrvhvrt.jpg","file_code":"3xif1ci7qvjg","length":"676","views":"751","uploaded":"2024-08-31 14:43:17","title":"Bokep Indo Adik Kakak Berkacamata Genjot Berdiri Bokepsin Com Doodflix Terabox Terupdate"},{"download_url":"https://myvidplay.com/d/wtc3hdioa8e5","single_img":"https://postercdn.net/snaps/brmqwq9yqa8xnv8h.jpg","file_code":"wtc3hdioa8e5","length":"117","views":"343","uploaded":"2024-08-31 14:43:17","title":"Bokep Indo Abg Smp Jilbab Coklat Masturbasi Bokepsin Com Tele Viral Bokepin"},{"download_url":"https://myvidplay.com/d/dz07n5t2pygn","single_img":"https://postercdn.net/snaps/dy3jk592wqlchdys.jpg","file_code":"dz07n5t2pygn","length":"377","views":"331","uploaded":"2024-08-31 14:43:17","title":"Bokep Indo Ngentot Hijab Kacamata Gemoy Semok Bokepsin Com Twitter Asupan Viral"},{"download_url":"https://myvidplay.com/d/20sky38u06n4","single_img":"https://postercdn.net/snaps/79bvaijl9lf778ou.jpg","file_code":"20sky38u06n4","length":"170","views":"355","uploaded":"2024-08-31 14:43:06","title":"Bokep Indo Jilbab Ijo Di Sofa Bokepsin Com Doods Pro Ngentot Viral"},{"download_url":"https://myvidplay.com/d/pdwim323birf","single_img":"https://postercdn.net/snaps/o40zaacpr15cx4gg.jpg","file_code":"pdwim323birf","length":"101","views":"538","uploaded":"2024-08-31 14:43:06","title":"Bokep Indo Mahasiswi Merintih Kesakitan Bokepsin Com Dood Tele Telegram Cilbo Link"},{"download_url":"https://myvidplay.com/d/0dbvl3e35tco","single_img":"https://postercdn.net/snaps/680zjphdkbcgn78e.jpg","file_code":"0dbvl3e35tco","length":"289","views":"242","uploaded":"2024-08-31 14:43:06","title":"Bokep Indo Langganan Psk Di Hotel Part Bokepsin Com Update Staklam Doodflix"},{"download_url":"https://myvidplay.com/d/1pofogxnc9b2","single_img":"https://postercdn.net/snaps/6r275cf3x4rmd8l0.jpg","file_code":"1pofogxnc9b2","length":"1845","views":"776","uploaded":"2024-08-31 14:43:06","title":"Bokep Indo Selingkuh Dengan Adik Ipar Lebih Memuaskan Bokepsin Com Dood Stream"},{"download_url":"https://myvidplay.com/d/w1v0427aqunq","single_img":"https://postercdn.net/snaps/1d7rrgnv8kqwyea8.jpg","file_code":"w1v0427aqunq","length":"3598","views":"824","uploaded":"2024-08-31 14:43:06","title":"Bokep Indo Vcs Meychen Pamerin Uting Coklat Bokepsin Com Bokepsatset Streaming Staklam"},{"download_url":"https://myvidplay.com/d/lp670rpyw82d","single_img":"https://postercdn.net/snaps/cmhsy8vh9rj8bi2o.jpg","file_code":"lp670rpyw82d","length":"465","views":"1595","uploaded":"2024-08-31 14:43:06","title":"Bokep Indo Hilda Selebgram Sange Bikin Video Colmek Bokepsin Com Ngentot Asupan"},{"download_url":"https://myvidplay.com/d/2pd0r08c96j3","single_img":"https://postercdn.net/snaps/a4jraruajmn30mlm.jpg","file_code":"2pd0r08c96j3","length":"542","views":"270","uploaded":"2024-08-31 14:43:06","title":"Bokep Indo Selesai Yoga Lanjut Colmek Bokepsin Com Cantik Tobrut Simontok Telegram"},{"download_url":"https://myvidplay.com/d/cgtu1yxcbh29","single_img":"https://postercdn.net/snaps/pawx2c7v6ac1uzg4.jpg","file_code":"cgtu1yxcbh29","length":"566","views":"367","uploaded":"2024-08-31 14:43:06","title":"Tante Princesss Bbw Crotin Dalem Mulut Bokepsin Com Video Viral Bokepsatset Tele"},{"download_url":"https://myvidplay.com/d/03s7n7ou3gdv","single_img":"https://postercdn.net/snaps/xfcdx57w7xolcu8k.jpg","file_code":"03s7n7ou3gdv","length":"2335","views":"644","uploaded":"2024-08-31 14:43:06","title":"Bokep Indo Kirana Si Jago Squirt Muncrat Bokepsin Com Memeksiana Bokep31 Asupan"},{"download_url":"https://myvidplay.com/d/0gg112tiqcsg","single_img":"https://postercdn.net/snaps/0ox1mue55lz7blo7.jpg","file_code":"0gg112tiqcsg","length":"1146","views":"3716","uploaded":"2024-08-31 14:43:06","title":"Bokep Indo Grepe Jilboobs Tobrut Ngewe Jagoaneonnn Bokepsin Com Tele Pekoblive Bochiel"},{"download_url":"https://myvidplay.com/d/ljpqhvtts3ui","single_img":"https://postercdn.net/snaps/jx1uo1naozqusps6.jpg","file_code":"ljpqhvtts3ui","length":"2361","views":"380","uploaded":"2024-08-31 14:43:06","title":"Bokep Indo Ukhty Alina Jilbab Biru Colmek Full Bokepsin Com Doostream Link"},{"download_url":"https://myvidplay.com/d/n2endzcbano4","single_img":"https://postercdn.net/snaps/zxvfgqn40ekdp46w.jpg","file_code":"n2endzcbano4","length":"503","views":"381","uploaded":"2024-08-31 14:43:06","title":"Bokep Indo Ukhty Omek Pake Belut Viral Bokepsin Com Telegram Lupa Mahkota"},{"download_url":"https://myvidplay.com/d/hgxgt0azqfej","single_img":"https://postercdn.net/snaps/lj8r0u5wr2ka4zkj.jpg","file_code":"hgxgt0azqfej","length":"73","views":"216","uploaded":"2024-08-31 14:43:06","title":"Bokep Indo Abg Twitter Susana Amelia Bokepsin Com Doodflix Pejuang Lendir Dood"},{"download_url":"https://myvidplay.com/d/q32m8nf5cq52","single_img":"https://postercdn.net/snaps/nrmfff6e00ktvsic.jpg","file_code":"q32m8nf5cq52","length":"200","views":"560","uploaded":"2024-08-31 14:43:06","title":"Bokep Ngentot Teman Kantor Sangean Bokepsin Doods Pro Dodstream Bokep31"},{"download_url":"https://myvidplay.com/d/ai2r7pz6yr5m","single_img":"https://postercdn.net/snaps/1g1pok2kavuxvqvu.jpg","file_code":"ai2r7pz6yr5m","length":"558","views":"369","uploaded":"2024-08-31 14:43:06","title":"Bokep Indo Dilayani Abg Cantik Toge Bokepsin Com Lulustream Twitter Links Bokepin"},{"download_url":"https://myvidplay.com/d/007ozuqwtfqe","single_img":"https://postercdn.net/snaps/r74llpcpb95hhdai.jpg","file_code":"007ozuqwtfqe","length":"85","views":"1209","uploaded":"2024-08-31 14:43:06","title":"Bokep Indo Ngentot Perawat Sange Di Rumah Sakit Bokepsin Com Videos Doodflix"},{"download_url":"https://myvidplay.com/d/9939hlr92dc8","single_img":"https://postercdn.net/snaps/exiwgshyksjhmp6q.jpg","file_code":"9939hlr92dc8","length":"118","views":"460","uploaded":"2024-08-31 14:43:06","title":"Viral Selegram Tiktok Cewe Cindo Di Masukin Rudal Full Album Cilbo Indo"},{"download_url":"https://myvidplay.com/d/yul3fxhv8dep","single_img":"https://postercdn.net/snaps/wcmzbbwgiz3csvq5.jpg","file_code":"yul3fxhv8dep","length":"95","views":"2980","uploaded":"2024-08-31 14:43:06","title":"Bokep Indo Viral Yang Katanya Rebecca Klopper Bokepsin Com Telegram Asupan Dood"},{"download_url":"https://myvidplay.com/d/s9kdl0wuxv15","single_img":"https://postercdn.net/snaps/3wdre554zvuih8dv.jpg","file_code":"s9kdl0wuxv15","length":"61","views":"438","uploaded":"2024-08-31 14:43:06","title":"Bokep Indo Vcs Hijab Toge Melayu Colmek Bokepsin Com Dood Stream Sotwe"},{"download_url":"https://myvidplay.com/d/y4765vndegx9","single_img":"https://postercdn.net/snaps/601kp9yv4r7qjgny.jpg","file_code":"y4765vndegx9","length":"473","views":"135","uploaded":"2024-08-31 14:43:06","title":"Bokep Indo Ngentot Photographer Abal Bokepsin Terupdate Video Viral Streaming"},{"download_url":"https://myvidplay.com/d/j23td091rm8u","single_img":"https://postercdn.net/snaps/khrd3u383wzaedr4.jpg","file_code":"j23td091rm8u","length":"361","views":"1423","uploaded":"2024-08-31 14:43:06","title":"Bokep Indo Mandi Kucing Sama Kakak Sepupu Bokepsin Com Bokepsatset Pemersatu Streaming"},{"download_url":"https://myvidplay.com/d/h9x6y2vuk0ze","single_img":"https://postercdn.net/snaps/479p5hws0248pxie.jpg","file_code":"h9x6y2vuk0ze","length":"2391","views":"1912","uploaded":"2024-08-31 14:43:06","title":"Bokep Live Cantik Cina Digilir Tukang Kebun Bokepsin Com Indonesia Sotwe Telegram"},{"download_url":"https://myvidplay.com/d/cwlvn60rsa3u","single_img":"https://postercdn.net/snaps/83fnsyo3fw6gmb0w.jpg","file_code":"cwlvn60rsa3u","length":"97","views":"1061","uploaded":"2024-08-31 14:43:06","title":"Bokep Indo Viral Syakirah Colmek Vcs Bokepsin Com Tobrut Video Telegram"},{"download_url":"https://myvidplay.com/d/795nqex0yd2e","single_img":"https://postercdn.net/snaps/ie5y2wkmk6t2cjym.jpg","file_code":"795nqex0yd2e","length":"938","views":"953","uploaded":"2024-08-31 14:43:06","title":"Bokep Indo Colok Memek Meychen Ngangkang Dildo Links Staklam Telegram Bokepind Viral"},{"download_url":"https://myvidplay.com/d/eoi8uhmirtqz","single_img":"https://postercdn.net/snaps/plbgrekyqe07kzpb.jpg","file_code":"eoi8uhmirtqz","length":"99","views":"719","uploaded":"2024-08-31 14:43:06","title":"Bokep Indo Tiktok Premium Laras Bali Terbaru Doods Pro Full Album Xpanas"},{"download_url":"https://myvidplay.com/d/9h146ikzdkw1","single_img":"https://postercdn.net/snaps/i373b145mx7expvz.jpg","file_code":"9h146ikzdkw1","length":"60","views":"652","uploaded":"2024-08-31 14:43:06","title":"Bokep Indo Jilbab Diyana Sakura Crot Di Muka Cantik Tobrut Lulustream Lokal"},{"download_url":"https://myvidplay.com/d/6tl28rs44s13","single_img":"https://postercdn.net/snaps/ijg9zxx4smzxc8tc.jpg","file_code":"6tl28rs44s13","length":"179","views":"373","uploaded":"2024-08-31 14:43:06","title":"Tiktokers Cantik Toket Gede Sering Fyp Toketbagus Ngentot Sotwe Bokepind Folder"},{"download_url":"https://myvidplay.com/d/80xacg8so8jv","single_img":"https://postercdn.net/snaps/wadlwcgbt7spxg2i.jpg","file_code":"80xacg8so8jv","length":"3149","views":"617","uploaded":"2024-08-31 14:43:06","title":"Bokep Liadani Live Prank Ngentot Ojol Telegram Links Asupan Viral Doodstreem"},{"download_url":"https://myvidplay.com/d/hqseh8b5g0v5","single_img":"https://postercdn.net/snaps/37rtc92gh85e4q3f.jpg","file_code":"hqseh8b5g0v5","length":"95","views":"367","uploaded":"2024-08-31 14:43:06","title":"Bokep Indo Doggystyle Karyawan Hijab Saat Sepi Bokepsin Com Terabox Twitter Dood"},{"download_url":"https://myvidplay.com/d/vbgt43s6vdy0","single_img":"https://postercdn.net/snaps/3tycw7lcaom58qpw.jpg","file_code":"vbgt43s6vdy0","length":"2238","views":"168","uploaded":"2024-08-31 14:43:06","title":"Bokep Indo Pov Disepong Chichiee Toge Mango Bokepsin Com Doodstreem Memeksiana Video"},{"download_url":"https://myvidplay.com/d/81owsivt6p28","single_img":"https://postercdn.net/snaps/l904y2dfiqd0o1no.jpg","file_code":"81owsivt6p28","length":"1524","views":"63","uploaded":"2024-08-31 14:43:00","title":"Bokep Indo Susu Gede Mulus Cici Tieu Boi Bokepsin Com Bokep31 Simontok"},{"download_url":"https://myvidplay.com/d/jre3xb84ein6","single_img":"https://postercdn.net/snaps/vtm16v5yhnydnpsy.jpg","file_code":"jre3xb84ein6","length":"184","views":"418","uploaded":"2024-08-31 14:43:00","title":"Bokep Indo Abg Hijab Panya Sange Omek Bokepsin Com Dood Stream Terupdate"},{"download_url":"https://myvidplay.com/d/mvb3xtrbla9t","single_img":"https://postercdn.net/snaps/14h05ncqtrhha75r.jpg","file_code":"mvb3xtrbla9t","length":"324","views":"114","uploaded":"2024-08-31 14:43:00","title":"Bokep Indo Ukhti Vicoletta Cosplay Karyawan Bank Bokepsin Com Doostream Bokepsatset Bebasindo"},{"download_url":"https://myvidplay.com/d/i73z8i5p8vkk","single_img":"https://postercdn.net/snaps/5zbzakw3uonw4p57.jpg","file_code":"i73z8i5p8vkk","length":"835","views":"849","uploaded":"2024-08-31 14:43:00","title":"Bokep Indo Ngewe Dua Sejoli Viral Part Pemersatu Jilbab Tobrut Full Album"},{"download_url":"https://myvidplay.com/d/72b116oazns4","single_img":"https://postercdn.net/snaps/4okrtf43lx9r76dy.jpg","file_code":"72b116oazns4","length":"806","views":"1289","uploaded":"2024-08-31 14:43:00","title":"Bokep Acha Tobrut Baju Merah Part Viral Bokepsin Com Full Album Pekoblive"},{"download_url":"https://myvidplay.com/d/5r78nsfyn7po","single_img":"https://postercdn.net/snaps/m53ybsobtiqathym.jpg","file_code":"5r78nsfyn7po","length":"903","views":"4974","uploaded":"2024-08-31 14:43:00","title":"Bokep Acha Tobrut Baju Merah Part Viral Bokepsin Com Cantik Update Doodsflix"},{"download_url":"https://myvidplay.com/d/f0w8m8xagzwz","single_img":"https://postercdn.net/snaps/odfydk9yh3s6iuf8.jpg","file_code":"f0w8m8xagzwz","length":"413","views":"756","uploaded":"2024-08-31 14:42:53","title":"Bokep Indo Ngentot Ukhti Ajirah Puspa Hijab Bokepsin Com Terupdate Tele Video"},{"download_url":"https://myvidplay.com/d/8n1c27ql763n","single_img":"https://postercdn.net/snaps/qp0magix9nj4kjn7.jpg","file_code":"8n1c27ql763n","length":"612","views":"181","uploaded":"2024-08-31 14:42:53","title":"Bokep Indo Ukhti Ain Ayuni Jilbab Viral Bokepsin Com Tiktok Ngentot Website"},{"download_url":"https://myvidplay.com/d/7v6m5fpl6jcx","single_img":"https://postercdn.net/snaps/g2vpzqc1qv8onl42.jpg","file_code":"7v6m5fpl6jcx","length":"62","views":"347","uploaded":"2024-08-31 14:42:53","title":"Bokep Indo Tante Toge Joe The Lego Konten Disepong Pekoblive Tiktok Lokal"},{"download_url":"https://myvidplay.com/d/1ipp9oh25uia","single_img":"https://postercdn.net/snaps/6epspr1vcy359x0c.jpg","file_code":"1ipp9oh25uia","length":"439","views":"335","uploaded":"2024-08-31 14:42:53","title":"Bokep Dipijat Wanita Jilbab Sampe Ngentod Bokepsin Com Telegram Tobrut Viral Terabox"},{"download_url":"https://myvidplay.com/d/1b13udryqvs8","single_img":"https://postercdn.net/snaps/bvede9lc3ynu9tfd.jpg","file_code":"1b13udryqvs8","length":"70","views":"306","uploaded":"2024-08-31 14:42:53","title":"Bokep Video Colmek Cewek Korea Toket Gede Bokepsin Com Yakwad Doostream Tobrut"},{"download_url":"https://myvidplay.com/d/zzx633f32amg","single_img":"https://postercdn.net/snaps/a4rg0imiotqzb5hi.jpg","file_code":"zzx633f32amg","length":"1020","views":"322","uploaded":"2024-08-31 14:42:53","title":"Bokep Indo Pamer Chacha Teki Pantat Susu Mulus Tele Bokepsin Ful Album"},{"download_url":"https://myvidplay.com/d/lonv185qh7ox","single_img":"https://postercdn.net/snaps/f5por4w8ny1ovdw5.jpg","file_code":"lonv185qh7ox","length":"237","views":"133","uploaded":"2024-08-31 14:42:53","title":"Bokep Idaman Abg Baby Isadora Jadi Host Pascol Bling Pekoblive Dood Tele"},{"download_url":"https://myvidplay.com/d/r921894xrgnp","single_img":"https://postercdn.net/snaps/jc0l57yy8m4qbx00.jpg","file_code":"r921894xrgnp","length":"107","views":"324","uploaded":"2024-08-31 14:42:53","title":"Bokep Indo Bocil Cindy Selebgram Viral Bokepsin Telegram Links Dood Lagi"},{"download_url":"https://myvidplay.com/d/jobk7tsiv0hc","single_img":"https://postercdn.net/snaps/tnxp7p2ln0z3f5k6.jpg","file_code":"jobk7tsiv0hc","length":"296","views":"587","uploaded":"2024-08-31 14:42:53","title":"Bokep Durasi Full Cewek Bali Tobrut Ngewe Viral Bokepsin Com Doodstreem Simintok"},{"download_url":"https://myvidplay.com/d/kwabaiwyi720","single_img":"https://postercdn.net/snaps/xt6h7avs6pl11ouk.jpg","file_code":"kwabaiwyi720","length":"810","views":"924","uploaded":"2024-08-31 14:42:53","title":"Bokep Indo Cewek Pernah Viral Di Ome Tv Bokepsin Video Pekoblive Doostream"},{"download_url":"https://myvidplay.com/d/oc5he5qv1h4c","single_img":"https://postercdn.net/snaps/o1kqspulsmkf1zxc.jpg","file_code":"oc5he5qv1h4c","length":"1542","views":"294","uploaded":"2024-08-31 14:42:53","title":"Bokep Citra Ukhty Viral Full Version Bokepsin Com Video Sotwe Update Doodsflix"},{"download_url":"https://myvidplay.com/d/2gmyc700v407","single_img":"https://postercdn.net/snaps/5dhkkvm3yjhu3ulb.jpg","file_code":"2gmyc700v407","length":"78","views":"286","uploaded":"2024-08-31 14:42:53","title":"Bokep Bocil Smp Viral Terbaru Bokepsin Com Popstream Bokepsatset Lagi Staklam Asupan"},{"download_url":"https://myvidplay.com/d/mjwv3t26gcvi","single_img":"https://postercdn.net/snaps/fbuyu0zd6v9hfb4c.jpg","file_code":"mjwv3t26gcvi","length":"127","views":"607","uploaded":"2024-08-31 14:42:53","title":"Bokep Indo Viral Spg Di Entod Anak Bos Bokepsin Com Doodstream Links"},{"download_url":"https://myvidplay.com/d/fukbb1256fy4","single_img":"https://postercdn.net/snaps/wx1uoxzadodo21h9.jpg","file_code":"fukbb1256fy4","length":"174","views":"547","uploaded":"2024-08-31 14:42:53","title":"Bokep Bunda Montok Viral Menjerit Manja Bokepsin Com Dood Stream Bokepsatset Doostream"},{"download_url":"https://myvidplay.com/d/8s51rngtbeax","single_img":"https://postercdn.net/snaps/xd7cqk4hts0n0kvh.jpg","file_code":"8s51rngtbeax","length":"367","views":"5552","uploaded":"2024-08-31 14:42:53","title":"Bokep Acha Tobrut Baju Merah Part Viral Bokepsin Com Full Album Lagi"},{"download_url":"https://myvidplay.com/d/6pt6yapzzrxc","single_img":"https://postercdn.net/snaps/krzk3i6kmckl5cpg.jpg","file_code":"6pt6yapzzrxc","length":"92","views":"258","uploaded":"2024-08-31 14:42:53","title":"Bokep Indo Tiktok Adinda Toket Gede Viral Telegram Lokal Full Album Tobrut"},{"download_url":"https://myvidplay.com/d/9wuxh7emokbj","single_img":"https://postercdn.net/snaps/ch0yzz8fnhuauysg.jpg","file_code":"9wuxh7emokbj","length":"65","views":"1375","uploaded":"2024-08-31 14:42:46","title":"Bokep Indo Sma Rara Nadifa Baju Pramuka Doodstream Jilbab Poophd Lulustream Bokepsatset"},{"download_url":"https://myvidplay.com/d/enn78252wt7e","single_img":"https://postercdn.net/snaps/a0ndcxb675vliqr1.jpg","file_code":"enn78252wt7e","length":"88","views":"1860","uploaded":"2024-08-31 14:42:46","title":"Bokep Indo Smp Rara Nadifa Di Kelas Sekolah Video Colmek Doodstream Lagi"},{"download_url":"https://myvidplay.com/d/usoa9bie8uky","single_img":"https://postercdn.net/snaps/ky191kxlv0c1d4q2.jpg","file_code":"usoa9bie8uky","length":"68","views":"128","uploaded":"2024-08-31 14:42:46","title":"Bokep Indo Tika Nesya Viral Tiktok Bokepsin Com Video Asupan Doostream Lagi"},{"download_url":"https://myvidplay.com/d/hwczni9qc7qf","single_img":"https://postercdn.net/snaps/gmd4pcohpzrmnj3f.jpg","file_code":"hwczni9qc7qf","length":"151","views":"767","uploaded":"2024-08-31 14:42:46","title":"Video Colmek Pake Jagung Memek Basah Raelilblack Bokepsin Com Popstream Memeksiana Bokep"},{"download_url":"https://myvidplay.com/d/7dk5132ii3ma","single_img":"https://postercdn.net/snaps/u33k8rbbcne1pdu3.jpg","file_code":"7dk5132ii3ma","length":"98","views":"2517","uploaded":"2024-08-31 14:42:46","title":"Viral Syakirah Colmek Vcs Bokep31 Pejuang Lendir Update Yakwad Simintok"},{"download_url":"https://myvidplay.com/d/qbt6bqrvbcq2","single_img":"https://postercdn.net/snaps/6el3ar5oyv14aanz.jpg","file_code":"qbt6bqrvbcq2","length":"302","views":"510","uploaded":"2024-08-31 14:42:46","title":"Bokep Indo Pelajar Smp Dientot Kakak Jemput Sekolah Bokepsin Com Twitter Terabox"},{"download_url":"https://myvidplay.com/d/cotdhkc8ubbb","single_img":"https://postercdn.net/snaps/hptwcq58yqzd99hp.jpg","file_code":"cotdhkc8ubbb","length":"915","views":"242","uploaded":"2024-08-31 14:42:46","title":"Bokep Dikasih Jatah Bibi Cantik Toket Gede Bokepsin Com Videos Doodstream Poophd"},{"download_url":"https://myvidplay.com/d/t89trkqsz305","single_img":"https://postercdn.net/snaps/fyzc8kj83l2wuobc.jpg","file_code":"t89trkqsz305","length":"137","views":"280","uploaded":"2024-08-31 14:42:46","title":"Bokep Indo Abg Kakak Adik Awalnya Iseng Jadi Ketagihan Link Web Twitter"},{"download_url":"https://myvidplay.com/d/6lq7ksriulve","single_img":"https://postercdn.net/snaps/enxct8hj9zyi6722.jpg","file_code":"6lq7ksriulve","length":"3718","views":"451","uploaded":"2024-08-31 14:42:46","title":"Bokep Dmx Shella Toge Montok Endingnya Telanjang Dada Bokepsin Com Streaming Poophd"},{"download_url":"https://myvidplay.com/d/brs1etrm282a","single_img":"https://postercdn.net/snaps/excpoov3l5tcf2fi.jpg","file_code":"brs1etrm282a","length":"5419","views":"3633","uploaded":"2024-08-31 14:42:46","title":"Bokep Indo Viral Siskaeee Keramat Tunggak Bokepsin Com Dodstream Bebasindo Simontok Folder"},{"download_url":"https://myvidplay.com/d/qt119o321h1g","single_img":"https://postercdn.net/snaps/7zdjlvv6isx5dgb1.jpg","file_code":"qt119o321h1g","length":"891","views":"2443","uploaded":"2024-08-31 14:42:46","title":"Bokep Acha Tobrut Baju Merah Part Viral Bokepsin Com Bokepin Website Asupan"},{"download_url":"https://myvidplay.com/d/cpi997vxdnrw","single_img":"https://postercdn.net/snaps/2c90tl1vaia80tqw.jpg","file_code":"cpi997vxdnrw","length":"61","views":"1184","uploaded":"2024-08-31 14:42:46","title":"Bokep Indo Hijab Camilla Memeknya Dijilatin Bokepsin Com Asupan Tiktok Terupdate Update"},{"download_url":"https://myvidplay.com/d/fezkk76t18sr","single_img":"https://postercdn.net/snaps/qy4wgkas4ys4hdm2.jpg","file_code":"fezkk76t18sr","length":"600","views":"2683","uploaded":"2024-08-31 14:42:46","title":"Bokep Indo Miss Kay Dientot Bokepsin Com Terabox Dodstream Indonesia Ful Album"},{"download_url":"https://myvidplay.com/d/bn0j6f4f8fma","single_img":"https://postercdn.net/snaps/pj6rd5p04xv2nm4d.jpg","file_code":"bn0j6f4f8fma","length":"63","views":"1032","uploaded":"2024-08-31 14:42:46","title":"Bokep Indo Miss Kay Colmek Squirt Video Terbaru Bokepsin Com Bokep31 Sma"},{"download_url":"https://myvidplay.com/d/4o0zdfhv1a98","single_img":"https://postercdn.net/snaps/o87ufzbjzdaoerar.jpg","file_code":"4o0zdfhv1a98","length":"300","views":"754","uploaded":"2024-08-31 14:42:46","title":"Bokep Indo Full Telanjang Miss Kay Colmek Squirt Bokepsin Com Video Videos"},{"download_url":"https://myvidplay.com/d/uxj01ekx6ucd","single_img":"https://postercdn.net/snaps/0zw4mjoc72xrzs0h.jpg","file_code":"uxj01ekx6ucd","length":"198","views":"596","uploaded":"2024-08-31 14:42:46","title":"Bokep Indo Ukhti Dipaksa Ngentot Pakai Kondom Bergerigi Bokepsin Com Memeksiana Links"},{"download_url":"https://myvidplay.com/d/dcctpc9p0thg","single_img":"https://postercdn.net/snaps/z6z7b120qjnqj9mx.jpg","file_code":"dcctpc9p0thg","length":"1056","views":"708","uploaded":"2024-08-31 14:42:46","title":"Bokep Indo Zelika Malang Pemuas Nafsu Dhiba Hijab Bokepsin Com Streaming Doodsflix"},{"download_url":"https://myvidplay.com/d/jlmqhxcuc8ro","single_img":"https://postercdn.net/snaps/d13546yfexjy6tym.jpg","file_code":"jlmqhxcuc8ro","length":"459","views":"272","uploaded":"2024-08-31 14:42:46","title":"Bokep Indo Irda Nelisa Full Video Bokepsin Com Dood Tele Simontok Popstream"},{"download_url":"https://myvidplay.com/d/5a65fr1bjumg","single_img":"https://postercdn.net/snaps/j760nqaoj44hz3n0.jpg","file_code":"5a65fr1bjumg","length":"443","views":"157","uploaded":"2024-08-31 14:42:46","title":"Bokep Indo Dhiba Hijab Zelika Malang Video Colmek Ngentot Telegram Indonesia"},{"download_url":"https://myvidplay.com/d/1ylf920sqqrm","single_img":"https://postercdn.net/snaps/ew1lcrn7zj85nc8o.jpg","file_code":"1ylf920sqqrm","length":"102","views":"845","uploaded":"2024-08-31 14:42:46","title":"Bokep Indo Syakirah Viral Part Full Video Bokepsin Com Doods Pro Links"},{"download_url":"https://myvidplay.com/d/mduduj1mr5kq","single_img":"https://postercdn.net/snaps/6r5msbegjs1it158.jpg","file_code":"mduduj1mr5kq","length":"64","views":"987","uploaded":"2024-08-31 14:42:46","title":"Bokep Indo Syakirah Viral Part Full Video Bokepsin Com Lagi Lokal Doodsflix"},{"download_url":"https://myvidplay.com/d/fz6rtwe41yse","single_img":"https://postercdn.net/snaps/3iboy4r9xm1f1xgt.jpg","file_code":"fz6rtwe41yse","length":"92","views":"1976","uploaded":"2024-08-31 14:42:46","title":"Bokep Syakirah Mandi Terbaru Bokepsin Com Viral Asupan Tele Links Ful Album"},{"download_url":"https://myvidplay.com/d/i3n5307mmkey","single_img":"https://postercdn.net/snaps/qdywypxjd0gyvh93.jpg","file_code":"i3n5307mmkey","length":"165","views":"1088","uploaded":"2024-08-31 14:42:46","title":"Bokep Indo Syakirah Viral Part Full Video Bokepsin Com Simontok Dood Tele"},{"download_url":"https://myvidplay.com/d/0hl0iptbk4w8","single_img":"https://postercdn.net/snaps/gbch4cymzf5w2xty.jpg","file_code":"0hl0iptbk4w8","length":"165","views":"1913","uploaded":"2024-08-31 14:42:46","title":"Bokep Indo Syakirah Tiktok Colmek Bokepsin Com Doodflix Simintok Pejuang Lendir"},{"download_url":"https://myvidplay.com/d/t52ru6wj1ni4","single_img":"https://postercdn.net/snaps/g4xl85ibjeey5cnm.jpg","file_code":"t52ru6wj1ni4","length":"305","views":"8809","uploaded":"2024-08-31 14:42:46","title":"Bokep Indo Syakirah Tiktok Viral Colmek Kamar Mandi Bokepsin Com Jilbab Telegram"},{"download_url":"https://myvidplay.com/d/53l9t1ix6mlo","single_img":"https://postercdn.net/snaps/ltqde6r0cql0s0iq.jpg","file_code":"53l9t1ix6mlo","length":"103","views":"3689","uploaded":"2024-08-31 14:42:46","title":"Bokep Indo Syakirah Pap Tt Colmek Terbaru Bokepsin Com Dood Stream Ngentot"},{"download_url":"https://myvidplay.com/d/2y16esp00t9z","single_img":"https://postercdn.net/snaps/mji0wrm83o1ps5k8.jpg","file_code":"2y16esp00t9z","length":"76","views":"9141","uploaded":"2024-08-31 14:42:46","title":"Bokep Indo Syakirah Viral Part Full Video Bokepsin Com Dood Stream Album"},{"download_url":"https://myvidplay.com/d/iscjm0l5fxcm","single_img":"https://postercdn.net/snaps/k377aqdor6nftpvi.jpg","file_code":"iscjm0l5fxcm","length":"185","views":"955","uploaded":"2024-08-31 14:42:46","title":"Bokep Jilbab Viral Abg Ngentot Di Gubuk Bokepsin Com Video Folder Bokepin"},{"download_url":"https://myvidplay.com/d/zb0qu0at12ou","single_img":"https://postercdn.net/snaps/eqjjymoum2y5fh3h.jpg","file_code":"zb0qu0at12ou","length":"2063","views":"2097","uploaded":"2024-08-31 14:42:40","title":"Bokep Tante Kina Ajarin Ponakan Duo Bugil Idaman Bokepsin Com Bebasindo Video"},{"download_url":"https://myvidplay.com/d/9ftr493sa9ux","single_img":"https://postercdn.net/snaps/z7h7gjvsfgr2p3cs.jpg","file_code":"9ftr493sa9ux","length":"613","views":"133","uploaded":"2024-08-31 14:42:40","title":"Bokep Cantik Pakai Lingerie Menggairahkan Bokepsin Com Dood Stream Doods Pro Videos"},{"download_url":"https://myvidplay.com/d/strjutc3lxde","single_img":"https://postercdn.net/snaps/gst6monpjer429bf.jpg","file_code":"strjutc3lxde","length":"358","views":"68","uploaded":"2024-08-31 14:42:40","title":"Bokep Indo Baby Shinta Toge Full Video Bokepsin Com Dood Stream Live"},{"download_url":"https://myvidplay.com/d/vw6aryvawyqd","single_img":"https://postercdn.net/snaps/onz61wv86rz3mw5y.jpg","file_code":"vw6aryvawyqd","length":"1142","views":"11786","uploaded":"2024-08-31 14:42:40","title":"Bokep Indo Viral Ciya Tiktok Full Video Bokepsin Com Dood Stream Doods"},{"download_url":"https://myvidplay.com/d/xxlrkdtivb7q","single_img":"https://postercdn.net/snaps/fdnqhpue3wvubj60.jpg","file_code":"xxlrkdtivb7q","length":"936","views":"487","uploaded":"2024-08-31 14:42:40","title":"Bokep Kompilasi Novi Sma Toge Colmek Video Viral Links Poophd Videos Xpanas"},{"download_url":"https://myvidplay.com/d/fjqtv287lfy1","single_img":"https://postercdn.net/snaps/7667wdzjc18t0oag.jpg","file_code":"fjqtv287lfy1","length":"105","views":"616","uploaded":"2024-08-31 14:42:40","title":"Bokep Ngentot Arni Abg Sma Lulustream Ful Album Video Viral Poophd"},{"download_url":"https://myvidplay.com/d/yu4n29gncpzs","single_img":"https://postercdn.net/snaps/rfw0qjanh04gqtzq.jpg","file_code":"yu4n29gncpzs","length":"97","views":"618","uploaded":"2024-08-31 14:42:40","title":"Bokep Kompilasi Fika Abg Sma Viral Video Popstream Simontok Ful Album Ngentot"},{"download_url":"https://myvidplay.com/d/16rjdapb9cf1","single_img":"https://postercdn.net/snaps/yyg52k0e7il2jo9o.jpg","file_code":"16rjdapb9cf1","length":"68","views":"320","uploaded":"2024-08-31 14:42:40","title":"Bokep Anak Lagi Sma Layani Ngentot Pacar Bokep31 Dood Tobrut Staklam"},{"download_url":"https://myvidplay.com/d/0gq809d0b00j","single_img":"https://postercdn.net/snaps/c48q2zebmxf7ulnd.jpg","file_code":"0gq809d0b00j","length":"273","views":"189","uploaded":"2024-08-31 14:42:40","title":"Bokep Abg Sma Pacar Minta Lihat Susu Video Colmek Viral Dood Tele"},{"download_url":"https://myvidplay.com/d/adou9a3g3ye9","single_img":"https://postercdn.net/snaps/vk6n0d64qx5nh1yc.jpg","file_code":"adou9a3g3ye9","length":"554","views":"1381","uploaded":"2024-08-31 14:42:40","title":"Bokep Abg Sma Tidur Di Grepe Om Sampe Ngentot Doodflix Sotwe Full"},{"download_url":"https://myvidplay.com/d/pc1y41z7fldw","single_img":"https://postercdn.net/snaps/b57srgfcek4mu1r8.jpg","file_code":"pc1y41z7fldw","length":"364","views":"559","uploaded":"2024-08-31 14:42:40","title":"Bokep Abg Sma Sepong Kontol Di Sekolah Doostream Sotwe Bokepin Bokep31 Staklam"},{"download_url":"https://myvidplay.com/d/8qy1xvd1x14g","single_img":"https://postercdn.net/snaps/g15brvbew1tltelf.jpg","file_code":"8qy1xvd1x14g","length":"121","views":"2764","uploaded":"2024-08-31 14:42:40","title":"Bokep Pelajar Sma Di Toilet Sampai Crot Dalem Viral Video Jilbab Lagi"},{"download_url":"https://myvidplay.com/d/c82ei2zn2wzt","single_img":"https://postercdn.net/snaps/ukc4fmr1j8fscobq.jpg","file_code":"c82ei2zn2wzt","length":"1318","views":"2604","uploaded":"2024-08-31 14:42:40","title":"Bokep Cewek Bocil Sma Di Gangbang Doodflix Update Indo Bokepind Lokal"},{"download_url":"https://myvidplay.com/d/78js8ux5ucxd","single_img":"https://postercdn.net/snaps/v812qbcwenl39j59.jpg","file_code":"78js8ux5ucxd","length":"1073","views":"1100","uploaded":"2024-08-31 14:42:40","title":"Bokep Mirip Kenzie Selebgram Cantik Imut Remas Toket Gede Terabox Tobrut Folder"},{"download_url":"https://myvidplay.com/d/tkidzuaal6g2","single_img":"https://postercdn.net/snaps/y0bj6gmwnwcqrui8.jpg","file_code":"tkidzuaal6g2","length":"126","views":"2218","uploaded":"2024-08-31 14:42:40","title":"Bokep Indo Perkosa Adik Cantik Toket Gede Nangis Asupan Video Viral Doodflix"},{"download_url":"https://myvidplay.com/d/s96w2hlq93pq","single_img":"https://postercdn.net/snaps/axoir21rz9penga1.jpg","file_code":"s96w2hlq93pq","length":"194","views":"613","uploaded":"2024-08-31 14:42:40","title":"Bokep Indo Pijit Ngentod Dengan Ayah Sendiri Live Video Sma Telegram Viral"},{"download_url":"https://myvidplay.com/d/drcy4r2vq1s5","single_img":"https://postercdn.net/snaps/b65cj61h3h5189nd.jpg","file_code":"drcy4r2vq1s5","length":"775","views":"479","uploaded":"2024-08-31 14:42:40","title":"Bokep Ajakin Pegawai Hotel Ngewe Di Kamar Staklam Cantik Tobrut Bokepsatset Viral"},{"download_url":"https://myvidplay.com/d/skda3zbgpl4n","single_img":"https://postercdn.net/snaps/1u8y3mf76dlpw3l4.jpg","file_code":"skda3zbgpl4n","length":"3149","views":"1922","uploaded":"2024-08-31 14:42:40","title":"Bokep Indo Liadani Live Prank Ojol Asupan Tobrut Indonesia Cantik Update"},{"download_url":"https://myvidplay.com/d/mwgyczq584d6","single_img":"https://postercdn.net/snaps/pqgvlcdzjkqhy2au.jpg","file_code":"mwgyczq584d6","length":"93","views":"328","uploaded":"2024-08-31 14:42:40","title":"Bokep Abg Cantik Lagi Pengen Akhirnya Colmek Jembut Lebat Website Bokepsin Doodflix"},{"download_url":"https://myvidplay.com/d/97ny1ii3dlp3","single_img":"https://postercdn.net/snaps/n1qiswz30ooh338x.jpg","file_code":"97ny1ii3dlp3","length":"117","views":"57","uploaded":"2024-08-31 14:42:40","title":"Bokep Cantik Puasin Ayang Di Hotel Nikmat Videos Doodstream Website Dodstream Video"},{"download_url":"https://myvidplay.com/d/500ivey1fxkm","single_img":"https://postercdn.net/snaps/eo10me9ucugxd4w8.jpg","file_code":"500ivey1fxkm","length":"342","views":"235","uploaded":"2024-08-31 14:42:40","title":"Bokep Kenikmatan Otong Di Sepong Ayang Cantik Video Indo Sma Update Sotwe"},{"download_url":"https://myvidplay.com/d/gzpbifz03sj0","single_img":"https://postercdn.net/snaps/6n4b22k2ly5qu5fx.jpg","file_code":"gzpbifz03sj0","length":"181","views":"719","uploaded":"2024-08-31 14:42:40","title":"Bokep Skandal Bu Guru Nakal Hijab Ngntod Sama Selingkuhan Di Hotel Dood"},{"download_url":"https://myvidplay.com/d/1f3yr3tyz9kb","single_img":"https://postercdn.net/snaps/6k20fs3e3ko2o1mj.jpg","file_code":"1f3yr3tyz9kb","length":"121","views":"246","uploaded":"2024-08-31 14:42:40","title":"Bokep Kakak Jilbab Di Ajak Teman Kantor Main Kosan Twitter Indonesia Toketbagus"},{"download_url":"https://myvidplay.com/d/lc3k33baz63g","single_img":"https://postercdn.net/snaps/7nmzv1k2vqslmfxe.jpg","file_code":"lc3k33baz63g","length":"125","views":"1151","uploaded":"2024-08-31 14:42:40","title":"Bokep Kata Ceweknya Anjing Enak Banget Indo Live Staklam Viral"},{"download_url":"https://myvidplay.com/d/juh2a6snxe29","single_img":"https://postercdn.net/snaps/r4l09bxmwd654nd9.jpg","file_code":"juh2a6snxe29","length":"122","views":"369","uploaded":"2024-08-31 14:42:40","title":"Bokep Karyawati Counter Ngewe Sama Majikan Ternyata Binor Doodflix Bochiel Doods Pro"},{"download_url":"https://myvidplay.com/d/mvxp3yhi58ls","single_img":"https://postercdn.net/snaps/bn24n2wgl4uu1vxh.jpg","file_code":"mvxp3yhi58ls","length":"1282","views":"353","uploaded":"2024-08-31 14:42:40","title":"Bokep Indo Milf Hot Wife Pasutri Threesome Video Bokepsin Toketbagus Twitter Doods"},{"download_url":"https://myvidplay.com/d/9hg0kantz6vh","single_img":"https://postercdn.net/snaps/johl6uh7hxqhxzgm.jpg","file_code":"9hg0kantz6vh","length":"119","views":"671","uploaded":"2024-08-31 14:42:40","title":"Panya Terbaru Viral Bokep Indo Doodstreem Bokep31 Pejuang Lendir Bochiel Video"},{"download_url":"https://myvidplay.com/d/jqv2k3bcrfb2","single_img":"https://postercdn.net/snaps/o3i7plcxq9zfcbv8.jpg","file_code":"jqv2k3bcrfb2","length":"91","views":"1499","uploaded":"2024-08-31 14:42:40","title":"Bokep Bocil Abg Mesum Di Gubuk Downloader Doostream Video Jilbab Lagi Viral"},{"download_url":"https://myvidplay.com/d/4aythme406ag","single_img":"https://postercdn.net/snaps/v7swgn5y7ee1i7ms.jpg","file_code":"4aythme406ag","length":"408","views":"73","uploaded":"2024-08-31 14:42:40","title":"Bokep Baby Metal Tobrut Sange Omek Terbaru Folder Sotwe Downloader Bokep31 Tele"},{"download_url":"https://myvidplay.com/d/gsozruem73iu","single_img":"https://postercdn.net/snaps/5s544x0p149un18x.jpg","file_code":"gsozruem73iu","length":"463","views":"228","uploaded":"2024-08-31 14:42:40","title":"Bokep Intip Tante Ngewe Suruh Rekam Malahan Tobrut Twitter Dood Video Viral"},{"download_url":"https://myvidplay.com/d/1kit0stgvxsb","single_img":"https://postercdn.net/snaps/hdb85uj7rk37octb.jpg","file_code":"1kit0stgvxsb","length":"320","views":"157","uploaded":"2024-08-31 14:42:40","title":"Bokep Cinta Tak Kenal Usia Ngentot Aja Asupan Viral Simintok Video Indo"},{"download_url":"https://myvidplay.com/d/suvtgwkh0w7c","single_img":"https://postercdn.net/snaps/hzb91ktguea51ka3.jpg","file_code":"suvtgwkh0w7c","length":"259","views":"123","uploaded":"2024-08-31 14:42:40","title":"Abg Si Cantik Binal Colmek Depan Cermin Bokep Indo Viral Tobrut Staklam"},{"download_url":"https://myvidplay.com/d/b76wemh8iqac","single_img":"https://postercdn.net/snaps/ccon8cljqnofnrbm.jpg","file_code":"b76wemh8iqac","length":"53","views":"498","uploaded":"2024-08-31 14:42:40","title":"Bokep Viral Colmek Bocil Awek Malay Bochiel Lokal Jilbab Video Sma Link"},{"download_url":"https://myvidplay.com/d/8ac983r2jo8a","single_img":"https://postercdn.net/snaps/w4p6rfcd80ham1ws.jpg","file_code":"8ac983r2jo8a","length":"126","views":"627","uploaded":"2024-08-31 14:42:40","title":"Bokep Ngentot Bocil Perawan Pacar Tetangga Staklam Cantik Tobrut Bokepsin Indo Asupan"},{"download_url":"https://myvidplay.com/d/4mvbjrqugd23","single_img":"https://postercdn.net/snaps/123ywtuqiuq4zfgu.jpg","file_code":"4mvbjrqugd23","length":"64","views":"770","uploaded":"2024-08-31 14:42:40","title":"Hijab Mesum Sama Doi Di Kebun Teh Bokep Indo Jilbab Viral"},{"download_url":"https://myvidplay.com/d/21xac02lk37r","single_img":"https://postercdn.net/snaps/7j0mx1gumh4f179v.jpg","file_code":"21xac02lk37r","length":"124","views":"261","uploaded":"2024-08-31 14:42:40","title":"Hijab Pink Sepong Kontol Panjang Bokep Indo Jilbab Viral Bokepsin Poophd Tele"},{"download_url":"https://myvidplay.com/d/vj4rv498rftv","single_img":"https://postercdn.net/snaps/zezonq3gzxdg41s4.jpg","file_code":"vj4rv498rftv","length":"71","views":"216","uploaded":"2024-08-31 14:42:40","title":"Cindo Pamer Memek Tembem Bikin Nagih Bokep Indo Viral Video Jilbab Pejuang"},{"download_url":"https://myvidplay.com/d/c9an5o4uwq1p","single_img":"https://postercdn.net/snaps/qiz622bwz2eggsdk.jpg","file_code":"c9an5o4uwq1p","length":"347","views":"242","uploaded":"2024-08-31 14:42:40","title":"Gadis Desa Bikin Video Mesum Bokep Indo Viral Bokepsin Staklam Cilbo Simontok"},{"download_url":"https://myvidplay.com/d/zjzq3xi5ssvh","single_img":"https://postercdn.net/snaps/98p63q5aez9wmsv5.jpg","file_code":"zjzq3xi5ssvh","length":"264","views":"1803","uploaded":"2024-08-31 04:44:48","title":"Bts Model Lydia Cantik Binal Pose Bugil Di Kamar Hot Tiktok Links"}]}