{"filecode":"1g6tpc6z8gjm","title":"Viral Ojol Ngonten Bokep Di Kuburan Ngentot Terupdate Tele Ful Album Downloader","deskripsi":"Nonton Viral Ojol Ngonten Bokep Di Kuburan Ngentot Terupdate Tele Ful Album Downloader gratis. Ukuran File: 520.00 MB, Durasi: 08:40. Populer: 1627 tayangan. Diunggah pada 2023-10-20 01:57:59 melalui doodstream. Kata Kunci Terkait: .","tag":null,"protected_embed":"https://dodl.pages.dev/1g6tpc6z8gjm","protected_dl":"https://myvidplay.com/d/1g6tpc6z8gjm","single_img":"https://postercdn.net/snaps/u3geenrudhvhdn3q.jpg","splash_img":"https://postercdn.net/splash/u3geenrudhvhdn3q.jpg","size":"545259520","length":"520","duration":"PT8M40S","views":"1627","uploaded":"2023-10-20 01:57:59","last_view":"2023-10-20 01:57:59","api_source":"doodstream","kategori":"Video Viral","page":93,"index":72}