{"filecode":"iv1kb1gxat0k","title":"Hijab Eh Ga Sengaja Keliatan Uting Full Video Doodstreem Live Asupan Viral","deskripsi":"Nonton Hijab Eh Ga Sengaja Keliatan Uting Full Video Doodstreem Live Asupan Viral gratis. Ukuran File: 270.00 MB, Durasi: 04:30. Populer: 194 tayangan. Diunggah pada 2025-01-13 05:20:15 melalui doodstream. Kata Kunci Terkait: .","tag":null,"protected_embed":"https://dodl.pages.dev/iv1kb1gxat0k","protected_dl":"https://myvidplay.com/d/iv1kb1gxat0k","single_img":"https://postercdn.net/snaps/zp1anmj5wsr8x8a7.jpg","splash_img":"https://postercdn.net/splash/zp1anmj5wsr8x8a7.jpg","size":"283115520","length":"270","duration":"PT4M30S","views":"194","uploaded":"2025-01-13 05:20:15","last_view":"2025-01-13 05:20:15","api_source":"doodstream","kategori":"Video Hijab","page":27,"index":2}