{"filecode":"uhvvjzc38c4f","title":"Ngentot Doggy Lc Karaoke Cantik Toge Doostream Full Album Jilbab Video Sma","deskripsi":"Nonton Ngentot Doggy Lc Karaoke Cantik Toge Doostream Full Album Jilbab Video Sma gratis. Ukuran File: 1.17 GB, Durasi: 20:03. Populer: 3093 tayangan. Diunggah pada 2024-08-31 04:43:14 melalui doodstream. Kata Kunci Terkait: .","tag":null,"protected_embed":"https://dodl.pages.dev/uhvvjzc38c4f","protected_dl":"https://myvidplay.com/d/uhvvjzc38c4f","single_img":"https://postercdn.net/snaps/8nob915sp1o6viq9.jpg","splash_img":"https://postercdn.net/splash/8nob915sp1o6viq9.jpg","size":"1261436928","length":"1203","duration":"PT20M3S","views":"3093","uploaded":"2024-08-31 04:43:14","last_view":"2024-08-31 04:43:14","api_source":"doodstream","kategori":"Video Sma","page":38,"index":156}