{"filecode":"rezwk710d20u","title":"Bokep Prank Ojol Kontol Gede Belum Tahu Doostream Website Cantik Tobrut Video","deskripsi":"Nonton Bokep Prank Ojol Kontol Gede Belum Tahu Doostream Website Cantik Tobrut Video gratis. Ukuran File: 1.31 GB, Durasi: 22:22. Populer: 5049 tayangan. Diunggah pada 2023-09-23 23:29:23 melalui doodstream. Kata Kunci Terkait: .","tag":null,"protected_embed":"https://dodl.pages.dev/rezwk710d20u","protected_dl":"https://myvidplay.com/d/rezwk710d20u","single_img":"https://postercdn.net/snaps/aiz4d65owyz8l2ky.jpg","splash_img":"https://postercdn.net/splash/aiz4d65owyz8l2ky.jpg","size":"1407188992","length":"1342","duration":"PT22M22S","views":"5049","uploaded":"2023-09-23 23:29:23","last_view":"2023-09-23 23:29:23","api_source":"doodstream","kategori":"Video Bokep","page":108,"index":193}