{"filecode":"dagd3r0spwms","title":"Suami Lagi Sakit Istri Berselingkuh Dengan Pria Lain Xpanas Live Ful Album","deskripsi":"Nonton Suami Lagi Sakit Istri Berselingkuh Dengan Pria Lain Xpanas Live Ful Album gratis. Ukuran File: 1.02 GB, Durasi: 17:28. Populer: 4189 tayangan. Diunggah pada 2023-10-19 21:56:53 melalui doodstream. Kata Kunci Terkait: .","tag":null,"protected_embed":"https://dodl.pages.dev/dagd3r0spwms","protected_dl":"https://myvidplay.com/d/dagd3r0spwms","single_img":"https://postercdn.net/snaps/t9gaa86gr1bi5rbp.jpg","splash_img":"https://postercdn.net/splash/t9gaa86gr1bi5rbp.jpg","size":"1098907648","length":"1048","duration":"PT17M28S","views":"4189","uploaded":"2023-10-19 21:56:53","last_view":"2023-10-19 21:56:53","api_source":"doodstream","kategori":"Video Live","page":93,"index":153}