{"filecode":"b4mah3wejb7a","title":"Menaklukkan Ibu Pacarku Doodsflix Video Bokep Update Viral Pemersatu","deskripsi":"Nonton Menaklukkan Ibu Pacarku Doodsflix Video Bokep Update Viral Pemersatu gratis. Ukuran File: 7.05 GB, Durasi: 02:00:16. Populer: 2753 tayangan. Diunggah pada 2023-08-26 14:09:27 melalui doodstream. Kata Kunci Terkait: .","tag":null,"protected_embed":"https://dodl.pages.dev/b4mah3wejb7a","protected_dl":"https://myvidplay.com/d/b4mah3wejb7a","single_img":"https://postercdn.net/snaps/scwtwkeh7p1qiqj4.jpg","splash_img":"https://postercdn.net/splash/scwtwkeh7p1qiqj4.jpg","size":"7566524416","length":"7216","duration":"PT120M16S","views":"2753","uploaded":"2023-08-26 14:09:27","last_view":"2023-08-26 14:09:27","api_source":"doodstream","kategori":"Video Viral","page":112,"index":15}