{"filecode":"ev4duivs7th6","title":"Siswi Smp Nyepong Kontol Di Kelas Lagi Viral Bokep Dood Folder Staklam","deskripsi":"Nonton Siswi Smp Nyepong Kontol Di Kelas Lagi Viral Bokep Dood Folder Staklam gratis. Ukuran File: 38.00 MB, Durasi: 00:38. Populer: 1349 tayangan. Diunggah pada 2023-10-08 02:47:14 melalui doodstream. Kata Kunci Terkait: .","tag":null,"protected_embed":"https://dodl.pages.dev/ev4duivs7th6","protected_dl":"https://myvidplay.com/d/ev4duivs7th6","single_img":"https://postercdn.net/snaps/c1ji31ur8ajgjaf4.jpg","splash_img":"https://postercdn.net/splash/c1ji31ur8ajgjaf4.jpg","size":"39845888","length":"38","duration":"PT38S","views":"1349","uploaded":"2023-10-08 02:47:14","last_view":"2023-10-08 02:47:14","api_source":"doodstream","kategori":"Video Viral","page":100,"index":192}