{"filecode":"idph0xapc9wd","title":"Bokep Abg Cantik Cobain Sensasi Ngewe Di Mobil Asupan Dodstream Website Dood","deskripsi":"Nonton Bokep Abg Cantik Cobain Sensasi Ngewe Di Mobil Asupan Dodstream Website Dood gratis. Ukuran File: 115.00 MB, Durasi: 01:55. Populer: 209 tayangan. Diunggah pada 2024-09-10 06:51:14 melalui doodstream. Kata Kunci Terkait: .","tag":null,"protected_embed":"https://dodl.pages.dev/idph0xapc9wd","protected_dl":"https://myvidplay.com/d/idph0xapc9wd","single_img":"https://postercdn.net/snaps/b8n94401aql76ref.jpg","splash_img":"https://postercdn.net/splash/b8n94401aql76ref.jpg","size":"120586240","length":"115","duration":"PT1M55S","views":"209","uploaded":"2024-09-10 06:51:14","last_view":"2024-09-10 06:51:14","api_source":"doodstream","kategori":"Video Dood","page":36,"index":119}