{"filecode":"qnn3mpjziinn","title":"Tingkah Laku Abg Kalo Rumah Gak Ada Org Ngewe Asupan Bokepin Lokal","deskripsi":"Nonton Tingkah Laku Abg Kalo Rumah Gak Ada Org Ngewe Asupan Bokepin Lokal gratis. Ukuran File: 216.00 MB, Durasi: 03:36. Populer: 2777 tayangan. Diunggah pada 2024-02-08 15:33:28 melalui doodstream. Kata Kunci Terkait: .","tag":null,"protected_embed":"https://dodl.pages.dev/qnn3mpjziinn","protected_dl":"https://myvidplay.com/d/qnn3mpjziinn","single_img":"https://postercdn.net/snaps/hddvro7m9oz09c5j.jpg","splash_img":"https://postercdn.net/splash/hddvro7m9oz09c5j.jpg","size":"226492416","length":"216","duration":"PT3M36S","views":"2777","uploaded":"2024-02-08 15:33:28","last_view":"2024-02-08 15:33:28","api_source":"doodstream","kategori":"Video Lokal","page":58,"index":105}