{"filecode":"vuhvyouhl5ue","title":"Ngewe Abg Memek Sempit Kesakitan Simontok Viral Telegram Terabox Doodstreem","deskripsi":"Nonton Ngewe Abg Memek Sempit Kesakitan Simontok Viral Telegram Terabox Doodstreem gratis. Ukuran File: 90.00 MB, Durasi: 01:30. Populer: 9805 tayangan. Diunggah pada 2023-12-16 00:27:36 melalui doodstream. Kata Kunci Terkait: .","tag":null,"protected_embed":"https://dodl.pages.dev/vuhvyouhl5ue","protected_dl":"https://myvidplay.com/d/vuhvyouhl5ue","single_img":"https://postercdn.net/snaps/aum52cutjws4rx7a.jpg","splash_img":"https://postercdn.net/splash/aum52cutjws4rx7a.jpg","size":"94371840","length":"90","duration":"PT1M30S","views":"9805","uploaded":"2023-12-16 00:27:36","last_view":"2023-12-16 00:27:36","api_source":"doodstream","kategori":"Video Viral","page":70,"index":13}