{"filecode":"v8x20c02zld0","title":"Niatnya Belajar Kelompok Malah Di Perkos Bokep Tobrut Bokep31 Bebasindo Dood","deskripsi":"Nonton Niatnya Belajar Kelompok Malah Di Perkos Bokep Tobrut Bokep31 Bebasindo Dood gratis. Ukuran File: 152.00 MB, Durasi: 02:32. Populer: 1722 tayangan. Diunggah pada 2024-12-31 10:43:31 melalui doodstream. Kata Kunci Terkait: .","tag":null,"protected_embed":"https://dodl.pages.dev/v8x20c02zld0","protected_dl":"https://myvidplay.com/d/v8x20c02zld0","single_img":"https://postercdn.net/snaps/68wyti638z60sdx2.jpg","splash_img":"https://postercdn.net/splash/68wyti638z60sdx2.jpg","size":"159383552","length":"152","duration":"PT2M32S","views":"1722","uploaded":"2024-12-31 10:43:31","last_view":"2024-12-31 10:43:31","api_source":"doodstream","kategori":"Video Dood","page":30,"index":0}