{"filecode":"tzuetf3pjoec","title":"Aksi Panas Abg Colmek Kacamata Hot Bebasindo Toketbagus Viral Video Bokep Twitter","deskripsi":"Nonton Aksi Panas Abg Colmek Kacamata Hot Bebasindo Toketbagus Viral Video Bokep Twitter gratis. Ukuran File: 606.00 MB, Durasi: 10:06. Populer: 4031 tayangan. Diunggah pada 2023-08-09 07:26:53 melalui doodstream. Kata Kunci Terkait: .","tag":null,"protected_embed":"https://dodl.pages.dev/tzuetf3pjoec","protected_dl":"https://myvidplay.com/d/tzuetf3pjoec","single_img":"https://postercdn.net/snaps/9h9rb4zoei9szyrr.jpg","splash_img":"https://postercdn.net/splash/9h9rb4zoei9szyrr.jpg","size":"635437056","length":"606","duration":"PT10M6S","views":"4031","uploaded":"2023-08-09 07:26:53","last_view":"2023-08-09 07:26:53","api_source":"doodstream","kategori":"Video Viral","page":118,"index":82}